{"1": {"acRate": 56.9925841916996, "difficulty": "Easy", "likes": 67350, "dislikes": 2504, "categoryTitle": "Algorithms", "frontendQuestionId": "1", "paidOnly": false, "title": "Two Sum", "titleSlug": "two-sum", "topicTags": [{"name": "Array", "id": "VG9waWNUYWdOb2RlOjU=", "slug": "array"}, {"name": "Hash Table", "id": "VG9waWNUYWdOb2RlOjY=", "slug": "hash-table"}], "hasSolution": true, "hasVideoSolution": true, "totalAcceptedRaw": 20583394, "totalSubmissionRaw": 36115954}, "2": {"acRate": 47.83864348679164, "difficulty": "Medium", "likes": 36169, "dislikes": 7162, "categoryTitle": "Algorithms", "frontendQuestionId": "2", "paidOnly": false, "title": "Add Two Numbers", "titleSlug": "add-two-numbers", "topicTags": [{"name": "Linked List", "id": "VG9waWNUYWdOb2RlOjc=", "slug": "linked-list"}, {"name": "Math", "id": "VG9waWNUYWdOb2RlOjg=", "slug": "math"}, {"name": "Recursion", "id": "VG9waWNUYWdOb2RlOjMx", "slug": "recursion"}], "hasSolution": true, "hasVideoSolution": true, "totalAcceptedRaw": 6709799, "totalSubmissionRaw": 14025906}, "3": {"acRate": 38.39122831997488, "difficulty": "Medium", "likes": 44349, "dislikes": 2181, "categoryTitle": "Algorithms", "frontendQuestionId": "3", "paidOnly": false, "title": "Longest Substring Without Repeating Characters", "titleSlug": "longest-substring-without-repeating-characters", "topicTags": [{"name": "Hash Table", "id": "VG9waWNUYWdOb2RlOjY=", "slug": "hash-table"}, {"name": "String", "id": "VG9waWNUYWdOb2RlOjEw", "slug": "string"}, {"name": "Sliding Window", "id": "VG9waWNUYWdOb2RlOjU1ODIx", "slug": "sliding-window"}], "hasSolution": true, "hasVideoSolution": true, "totalAcceptedRaw": 8932736, "totalSubmissionRaw": 23267663}, "4": {"acRate": 45.79995696485255, "difficulty": "Hard", "likes": 31739, "dislikes": 3547, "categoryTitle": "Algorithms", "frontendQuestionId": "4", "paidOnly": false, "title": "Median of Two Sorted Arrays", "titleSlug": "median-of-two-sorted-arrays", "topicTags": [{"name": "Array", "id": "VG9waWNUYWdOb2RlOjU=", "slug": "array"}, {"name": "Binary Search", "id": "VG9waWNUYWdOb2RlOjEx", "slug": "binary-search"}, {"name": "Divide and Conquer", "id": "VG9waWNUYWdOb2RlOjEy", "slug": "divide-and-conquer"}], "hasSolution": true, "hasVideoSolution": true, "totalAcceptedRaw": 4033476, "totalSubmissionRaw": 8806733}, "5": {"acRate": 37.21324227685244, "difficulty": "Medium", "likes": 32277, "dislikes": 1986, "categoryTitle": "Algorithms", "frontendQuestionId": "5", "paidOnly": false, "title": "Longest Palindromic Substring", "titleSlug": "longest-palindromic-substring", "topicTags": [{"name": "Two Pointers", "id": "VG9waWNUYWdOb2RlOjk=", "slug": "two-pointers"}, {"name": "String", "id": "VG9waWNUYWdOb2RlOjEw", "slug": "string"}, {"name": "Dynamic Programming", "id": "VG9waWNUYWdOb2RlOjEz", "slug": "dynamic-programming"}], "hasSolution": true, "hasVideoSolution": true, "totalAcceptedRaw": 4506400, "totalSubmissionRaw": 12109676}, "6": {"acRate": 53.416066584995804, "difficulty": "Medium", "likes": 9203, "dislikes": 15815, "categoryTitle": "Algorithms", "frontendQuestionId": "6", "paidOnly": false, "title": "Zigzag Conversion", "titleSlug": "zigzag-conversion", "topicTags": [{"name": "String", "id": "VG9waWNUYWdOb2RlOjEw", "slug": "string"}], "hasSolution": true, "hasVideoSolution": true, "totalAcceptedRaw": 2091621, "totalSubmissionRaw": 3915715}, "7": {"acRate": 31.428931722016586, "difficulty": "Medium", "likes": 15267, "dislikes": 13977, "categoryTitle": "Algorithms", "frontendQuestionId": "7", "paidOnly": false, "title": "Reverse Integer", "titleSlug": "reverse-integer", "topicTags": [{"name": "Math", "id": "VG9waWNUYWdOb2RlOjg=", "slug": "math"}], "hasSolution": true, "hasVideoSolution": true, "totalAcceptedRaw": 4762838, "totalSubmissionRaw": 15154310}, "8": {"acRate": 20.49101774142659, "difficulty": "Medium", "likes": 6059, "dislikes": 15478, "categoryTitle": "Algorithms", "frontendQuestionId": "8", "paidOnly": false, "title": "String to Integer (atoi)", "titleSlug": "string-to-integer-atoi", "topicTags": [{"name": "String", "id": "VG9waWNUYWdOb2RlOjEw", "slug": "string"}], "hasSolution": true, "hasVideoSolution": false, "totalAcceptedRaw": 2325655, "totalSubmissionRaw": 11349638}, "9": {"acRate": 60.18701767444363, "difficulty": "Easy", "likes": 15575, "dislikes": 2910, "categoryTitle": "Algorithms", "frontendQuestionId": "9", "paidOnly": false, "title": "Palindrome Number", "titleSlug": "palindrome-number", "topicTags": [{"name": "Math", "id": "VG9waWNUYWdOb2RlOjg=", "slug": "math"}], "hasSolution": true, "hasVideoSolution": true, "totalAcceptedRaw": 7694687, "totalSubmissionRaw": 12784636}, "10": {"acRate": 30.341160184680316, "difficulty": "Hard", "likes": 13218, "dislikes": 2384, "categoryTitle": "Algorithms", "frontendQuestionId": "10", "paidOnly": false, "title": "Regular Expression Matching", "titleSlug": "regular-expression-matching", "topicTags": [{"name": "String", "id": "VG9waWNUYWdOb2RlOjEw", "slug": "string"}, {"name": "Dynamic Programming", "id": "VG9waWNUYWdOb2RlOjEz", "slug": "dynamic-programming"}, {"name": "Recursion", "id": "VG9waWNUYWdOb2RlOjMx", "slug": "recursion"}], "hasSolution": true, "hasVideoSolution": false, "totalAcceptedRaw": 1327134, "totalSubmissionRaw": 4374036}, "11": {"acRate": 59.427230923201776, "difficulty": "Medium", "likes": 33708, "dislikes": 2171, "categoryTitle": "Algorithms", "frontendQuestionId": "11", "paidOnly": false, "title": "Container With Most Water", "titleSlug": "container-with-most-water", "topicTags": [{"name": "Array", "id": "VG9waWNUYWdOb2RlOjU=", "slug": "array"}, {"name": "Two Pointers", "id": "VG9waWNUYWdOb2RlOjk=", "slug": "two-pointers"}, {"name": "Greedy", "id": "VG9waWNUYWdOb2RlOjE3", "slug": "greedy"}], "hasSolution": true, "hasVideoSolution": true, "totalAcceptedRaw": 5037111, "totalSubmissionRaw": 8476094}, "12": {"acRate": 70.31888984701465, "difficulty": "Medium", "likes": 8434, "dislikes": 5714, "categoryTitle": "Algorithms", "frontendQuestionId": "12", "paidOnly": false, "title": "Integer to Roman", "titleSlug": "integer-to-roman", "topicTags": [{"name": "Hash Table", "id": "VG9waWNUYWdOb2RlOjY=", "slug": "hash-table"}, {"name": "Math", "id": "VG9waWNUYWdOb2RlOjg=", "slug": "math"}, {"name": "String", "id": "VG9waWNUYWdOb2RlOjEw", "slug": "string"}], "hasSolution": true, "hasVideoSolution": true, "totalAcceptedRaw": 2032951, "totalSubmissionRaw": 2891047}, "13": {"acRate": 66.16585532592875, "difficulty": "Easy", "likes": 17415, "dislikes": 1208, "categoryTitle": "Algorithms", "frontendQuestionId": "13", "paidOnly": false, "title": "Roman to Integer", "titleSlug": "roman-to-integer", "topicTags": [{"name": "Hash Table", "id": "VG9waWNUYWdOb2RlOjY=", "slug": "hash-table"}, {"name": "Math", "id": "VG9waWNUYWdOb2RlOjg=", "slug": "math"}, {"name": "String", "id": "VG9waWNUYWdOb2RlOjEw", "slug": "string"}], "hasSolution": true, "hasVideoSolution": true, "totalAcceptedRaw": 5621319, "totalSubmissionRaw": 8495793}, "14": {"acRate": 46.99460061541373, "difficulty": "Easy", "likes": 20973, "dislikes": 4898, "categoryTitle": "Algorithms", "frontendQuestionId": "14", "paidOnly": false, "title": "Longest Common Prefix", "titleSlug": "longest-common-prefix", "topicTags": [{"name": "Array", "id": "VG9waWNUYWdOb2RlOjU=", "slug": "array"}, {"name": "String", "id": "VG9waWNUYWdOb2RlOjEw", "slug": "string"}, {"name": "Trie", "id": "VG9waWNUYWdOb2RlOjI3", "slug": "trie"}], "hasSolution": true, "hasVideoSolution": true, "totalAcceptedRaw": 5463725, "totalSubmissionRaw": 11626281}, "15": {"acRate": 38.49250336330566, "difficulty": "Medium", "likes": 35064, "dislikes": 3253, "categoryTitle": "Algorithms", "frontendQuestionId": "15", "paidOnly": false, "title": "3Sum", "titleSlug": "3sum", "topicTags": [{"name": "Array", "id": "VG9waWNUYWdOb2RlOjU=", "slug": "array"}, {"name": "Two Pointers", "id": "VG9waWNUYWdOb2RlOjk=", "slug": "two-pointers"}, {"name": "Sorting", "id": "VG9waWNUYWdOb2RlOjYxMDQ5", "slug": "sorting"}], "hasSolution": true, "hasVideoSolution": true, "totalAcceptedRaw": 5629700, "totalSubmissionRaw": 14625447}, "16": {"acRate": 47.951981393506976, "difficulty": "Medium", "likes": 11519, "dislikes": 616, "categoryTitle": "Algorithms", "frontendQuestionId": "16", "paidOnly": false, "title": "3Sum Closest", "titleSlug": "3sum-closest", "topicTags": [{"name": "Array", "id": "VG9waWNUYWdOb2RlOjU=", "slug": "array"}, {"name": "Two Pointers", "id": "VG9waWNUYWdOb2RlOjk=", "slug": "two-pointers"}, {"name": "Sorting", "id": "VG9waWNUYWdOb2RlOjYxMDQ5", "slug": "sorting"}], "hasSolution": true, "hasVideoSolution": true, "totalAcceptedRaw": 1738859, "totalSubmissionRaw": 3626254}, "17": {"acRate": 65.39666577635428, "difficulty": "Medium", "likes": 20731, "dislikes": 1121, "categoryTitle": "Algorithms", "frontendQuestionId": "17", "paidOnly": false, "title": "Letter Combinations of a Phone Number", "titleSlug": "letter-combinations-of-a-phone-number", "topicTags": [{"name": "Hash Table", "id": "VG9waWNUYWdOb2RlOjY=", "slug": "hash-table"}, {"name": "String", "id": "VG9waWNUYWdOb2RlOjEw", "slug": "string"}, {"name": "Backtracking", "id": "VG9waWNUYWdOb2RlOjE0", "slug": "backtracking"}], "hasSolution": true, "hasVideoSolution": false, "totalAcceptedRaw": 2896519, "totalSubmissionRaw": 4429153}, "18": {"acRate": 39.87375712351626, "difficulty": "Medium", "likes": 12725, "dislikes": 1530, "categoryTitle": "Algorithms", "frontendQuestionId": "18", "paidOnly": false, "title": "4Sum", "titleSlug": "4sum", "topicTags": [{"name": "Array", "id": "VG9waWNUYWdOb2RlOjU=", "slug": "array"}, {"name": "Two Pointers", "id": "VG9waWNUYWdOb2RlOjk=", "slug": "two-pointers"}, {"name": "Sorting", "id": "VG9waWNUYWdOb2RlOjYxMDQ5", "slug": "sorting"}], "hasSolution": true, "hasVideoSolution": false, "totalAcceptedRaw": 1583038, "totalSubmissionRaw": 3970126}, "19": {"acRate": 50.86488305952555, "difficulty": "Medium", "likes": 21038, "dislikes": 891, "categoryTitle": "Algorithms", "frontendQuestionId": "19", "paidOnly": false, "title": "Remove Nth Node From End of List", "titleSlug": "remove-nth-node-from-end-of-list", "topicTags": [{"name": "Linked List", "id": "VG9waWNUYWdOb2RlOjc=", "slug": "linked-list"}, {"name": "Two Pointers", "id": "VG9waWNUYWdOb2RlOjk=", "slug": "two-pointers"}], "hasSolution": true, "hasVideoSolution": true, "totalAcceptedRaw": 4022619, "totalSubmissionRaw": 7908448}, "20": {"acRate": 43.618723806162244, "difficulty": "Easy", "likes": 27472, "dislikes": 1983, "categoryTitle": "Algorithms", "frontendQuestionId": "20", "paidOnly": false, "title": "Valid Parentheses", "titleSlug": "valid-parentheses", "topicTags": [{"name": "String", "id": "VG9waWNUYWdOb2RlOjEw", "slug": "string"}, {"name": "Stack", "id": "VG9waWNUYWdOb2RlOjE1", "slug": "stack"}], "hasSolution": true, "hasVideoSolution": true, "totalAcceptedRaw": 7174912, "totalSubmissionRaw": 16449166}, "21": {"acRate": 67.85568614434867, "difficulty": "Easy", "likes": 24669, "dislikes": 2421, "categoryTitle": "Algorithms", "frontendQuestionId": "21", "paidOnly": false, "title": "Merge Two Sorted Lists", "titleSlug": "merge-two-sorted-lists", "topicTags": [{"name": "Linked List", "id": "VG9waWNUYWdOb2RlOjc=", "slug": "linked-list"}, {"name": "Recursion", "id": "VG9waWNUYWdOb2RlOjMx", "slug": "recursion"}], "hasSolution": true, "hasVideoSolution": true, "totalAcceptedRaw": 6002323, "totalSubmissionRaw": 8845722}, "22": {"acRate": 78.19717149331231, "difficulty": "Medium", "likes": 23074, "dislikes": 1072, "categoryTitle": "Algorithms", "frontendQuestionId": "22", "paidOnly": false, "title": "Generate Parentheses", "titleSlug": "generate-parentheses", "topicTags": [{"name": "String", "id": "VG9waWNUYWdOb2RlOjEw", "slug": "string"}, {"name": "Dynamic Programming", "id": "VG9waWNUYWdOb2RlOjEz", "slug": "dynamic-programming"}, {"name": "Backtracking", "id": "VG9waWNUYWdOb2RlOjE0", "slug": "backtracking"}], "hasSolution": true, "hasVideoSolution": true, "totalAcceptedRaw": 2752165, "totalSubmissionRaw": 3519521}, "23": {"acRate": 58.74397330774222, "difficulty": "Hard", "likes": 21137, "dislikes": 787, "categoryTitle": "Algorithms", "frontendQuestionId": "23", "paidOnly": false, "title": "Merge k Sorted Lists", "titleSlug": "merge-k-sorted-lists", "topicTags": [{"name": "Linked List", "id": "VG9waWNUYWdOb2RlOjc=", "slug": "linked-list"}, {"name": "Divide and Conquer", "id": "VG9waWNUYWdOb2RlOjEy", "slug": "divide-and-conquer"}, {"name": "Heap (Priority Queue)", "id": "VG9waWNUYWdOb2RlOjYxMDUw", "slug": "heap-priority-queue"}, {"name": "Merge Sort", "id": "VG9waWNUYWdOb2RlOjYxMDUx", "slug": "merge-sort"}], "hasSolution": true, "hasVideoSolution": true, "totalAcceptedRaw": 2858029, "totalSubmissionRaw": 4865230}, "24": {"acRate": 68.83603968393498, "difficulty": "Medium", "likes": 13028, "dislikes": 507, "categoryTitle": "Algorithms", "frontendQuestionId": "24", "paidOnly": false, "title": "Swap Nodes in Pairs", "titleSlug": "swap-nodes-in-pairs", "topicTags": [{"name": "Linked List", "id": "VG9waWNUYWdOb2RlOjc=", "slug": "linked-list"}, {"name": "Recursion", "id": "VG9waWNUYWdOb2RlOjMx", "slug": "recursion"}], "hasSolution": true, "hasVideoSolution": false, "totalAcceptedRaw": 1844160, "totalSubmissionRaw": 2679064}, "25": {"acRate": 65.2009083211454, "difficulty": "Hard", "likes": 15487, "dislikes": 797, "categoryTitle": "Algorithms", "frontendQuestionId": "25", "paidOnly": false, "title": "Reverse Nodes in k-Group", "titleSlug": "reverse-nodes-in-k-group", "topicTags": [{"name": "Linked List", "id": "VG9waWNUYWdOb2RlOjc=", "slug": "linked-list"}, {"name": "Recursion", "id": "VG9waWNUYWdOb2RlOjMx", "slug": "recursion"}], "hasSolution": true, "hasVideoSolution": false, "totalAcceptedRaw": 1456884, "totalSubmissionRaw": 2234453}, "26": {"acRate": 62.149164671928304, "difficulty": "Easy", "likes": 18653, "dislikes": 20437, "categoryTitle": "Algorithms", "frontendQuestionId": "26", "paidOnly": false, "title": "Remove Duplicates from Sorted Array", "titleSlug": "remove-duplicates-from-sorted-array", "topicTags": [{"name": "Array", "id": "VG9waWNUYWdOb2RlOjU=", "slug": "array"}, {"name": "Two Pointers", "id": "VG9waWNUYWdOb2RlOjk=", "slug": "two-pointers"}], "hasSolution": true, "hasVideoSolution": true, "totalAcceptedRaw": 7446636, "totalSubmissionRaw": 11981884}, "27": {"acRate": 61.27753250820337, "difficulty": "Easy", "likes": 4891, "dislikes": 5265, "categoryTitle": "Algorithms", "frontendQuestionId": "27", "paidOnly": false, "title": "Remove Element", "titleSlug": "remove-element", "topicTags": [{"name": "Array", "id": "VG9waWNUYWdOb2RlOjU=", "slug": "array"}, {"name": "Two Pointers", "id": "VG9waWNUYWdOb2RlOjk=", "slug": "two-pointers"}], "hasSolution": true, "hasVideoSolution": true, "totalAcceptedRaw": 4977866, "totalSubmissionRaw": 8123473}, "28": {"acRate": 46.173829420536876, "difficulty": "Easy", "likes": 7465, "dislikes": 566, "categoryTitle": "Algorithms", "frontendQuestionId": "28", "paidOnly": false, "title": "Find the Index of the First Occurrence in a String", "titleSlug": "find-the-index-of-the-first-occurrence-in-a-string", "topicTags": [{"name": "Two Pointers", "id": "VG9waWNUYWdOb2RlOjk=", "slug": "two-pointers"}, {"name": "String", "id": "VG9waWNUYWdOb2RlOjEw", "slug": "string"}, {"name": "String Matching", "id": "VG9waWNUYWdOb2RlOjYxMDUy", "slug": "string-matching"}], "hasSolution": true, "hasVideoSolution": true, "totalAcceptedRaw": 3881481, "totalSubmissionRaw": 8406247}, "29": {"acRate": 19.31290126197677, "difficulty": "Medium", "likes": 6032, "dislikes": 15256, "categoryTitle": "Algorithms", "frontendQuestionId": "29", "paidOnly": false, "title": "Divide Two Integers", "titleSlug": "divide-two-integers", "topicTags": [{"name": "Math", "id": "VG9waWNUYWdOb2RlOjg=", "slug": "math"}, {"name": "Bit Manipulation", "id": "VG9waWNUYWdOb2RlOjE5", "slug": "bit-manipulation"}], "hasSolution": true, "hasVideoSolution": false, "totalAcceptedRaw": 1106518, "totalSubmissionRaw": 5729424}, "30": {"acRate": 33.89497829328067, "difficulty": "Hard", "likes": 2577, "dislikes": 423, "categoryTitle": "Algorithms", "frontendQuestionId": "30", "paidOnly": false, "title": "Substring with Concatenation of All Words", "titleSlug": "substring-with-concatenation-of-all-words", "topicTags": [{"name": "Hash Table", "id": "VG9waWNUYWdOb2RlOjY=", "slug": "hash-table"}, {"name": "String", "id": "VG9waWNUYWdOb2RlOjEw", "slug": "string"}, {"name": "Sliding Window", "id": "VG9waWNUYWdOb2RlOjU1ODIx", "slug": "sliding-window"}], "hasSolution": true, "hasVideoSolution": true, "totalAcceptedRaw": 675894, "totalSubmissionRaw": 1994083}, "31": {"acRate": 44.64327395025471, "difficulty": "Medium", "likes": 21132, "dislikes": 5085, "categoryTitle": "Algorithms", "frontendQuestionId": "31", "paidOnly": false, "title": "Next Permutation", "titleSlug": "next-permutation", "topicTags": [{"name": "Array", "id": "VG9waWNUYWdOb2RlOjU=", "slug": "array"}, {"name": "Two Pointers", "id": "VG9waWNUYWdOb2RlOjk=", "slug": "two-pointers"}], "hasSolution": true, "hasVideoSolution": true, "totalAcceptedRaw": 2161277, "totalSubmissionRaw": 4841206}, "32": {"acRate": 37.89068189575149, "difficulty": "Hard", "likes": 13212, "dislikes": 461, "categoryTitle": "Algorithms", "frontendQuestionId": "32", "paidOnly": false, "title": "Longest Valid Parentheses", "titleSlug": "longest-valid-parentheses", "topicTags": [{"name": "String", "id": "VG9waWNUYWdOb2RlOjEw", "slug": "string"}, {"name": "Dynamic Programming", "id": "VG9waWNUYWdOb2RlOjEz", "slug": "dynamic-programming"}, {"name": "Stack", "id": "VG9waWNUYWdOb2RlOjE1", "slug": "stack"}], "hasSolution": true, "hasVideoSolution": false, "totalAcceptedRaw": 1045774, "totalSubmissionRaw": 2759978}, "33": {"acRate": 44.034517923561914, "difficulty": "Medium", "likes": 29646, "dislikes": 1795, "categoryTitle": "Algorithms", "frontendQuestionId": "33", "paidOnly": false, "title": "Search in Rotated Sorted Array", "titleSlug": "search-in-rotated-sorted-array", "topicTags": [{"name": "Array", "id": "VG9waWNUYWdOb2RlOjU=", "slug": "array"}, {"name": "Binary Search", "id": "VG9waWNUYWdOb2RlOjEx", "slug": "binary-search"}], "hasSolution": true, "hasVideoSolution": false, "totalAcceptedRaw": 4223884, "totalSubmissionRaw": 9592214}, "34": {"acRate": 48.247210516415485, "difficulty": "Medium", "likes": 23027, "dislikes": 631, "categoryTitle": "Algorithms", "frontendQuestionId": "34", "paidOnly": false, "title": "Find First and Last Position of Element in Sorted Array", "titleSlug": "find-first-and-last-position-of-element-in-sorted-array", "topicTags": [{"name": "Array", "id": "VG9waWNUYWdOb2RlOjU=", "slug": "array"}, {"name": "Binary Search", "id": "VG9waWNUYWdOb2RlOjEx", "slug": "binary-search"}], "hasSolution": true, "hasVideoSolution": false, "totalAcceptedRaw": 3152252, "totalSubmissionRaw": 6533541}, "35": {"acRate": 50.590206051055674, "difficulty": "Easy", "likes": 18563, "dislikes": 884, "categoryTitle": "Algorithms", "frontendQuestionId": "35", "paidOnly": false, "title": "Search Insert Position", "titleSlug": "search-insert-position", "topicTags": [{"name": "Array", "id": "VG9waWNUYWdOb2RlOjU=", "slug": "array"}, {"name": "Binary Search", "id": "VG9waWNUYWdOb2RlOjEx", "slug": "binary-search"}], "hasSolution": true, "hasVideoSolution": true, "totalAcceptedRaw": 4507430, "totalSubmissionRaw": 8909688}, "36": {"acRate": 64.07685519338587, "difficulty": "Medium", "likes": 12357, "dislikes": 1259, "categoryTitle": "Algorithms", "frontendQuestionId": "36", "paidOnly": false, "title": "Valid Sudoku", "titleSlug": "valid-sudoku", "topicTags": [{"name": "Array", "id": "VG9waWNUYWdOb2RlOjU=", "slug": "array"}, {"name": "Hash Table", "id": "VG9waWNUYWdOb2RlOjY=", "slug": "hash-table"}, {"name": "Matrix", "id": "VG9waWNUYWdOb2RlOjYxMDUz", "slug": "matrix"}], "hasSolution": true, "hasVideoSolution": false, "totalAcceptedRaw": 2395383, "totalSubmissionRaw": 3738299}, "37": {"acRate": 65.36509651855148, "difficulty": "Hard", "likes": 10980, "dislikes": 339, "categoryTitle": "Algorithms", "frontendQuestionId": "37", "paidOnly": false, "title": "Sudoku Solver", "titleSlug": "sudoku-solver", "topicTags": [{"name": "Array", "id": "VG9waWNUYWdOb2RlOjU=", "slug": "array"}, {"name": "Hash Table", "id": "VG9waWNUYWdOb2RlOjY=", "slug": "hash-table"}, {"name": "Backtracking", "id": "VG9waWNUYWdOb2RlOjE0", "slug": "backtracking"}, {"name": "Matrix", "id": "VG9waWNUYWdOb2RlOjYxMDUz", "slug": "matrix"}], "hasSolution": true, "hasVideoSolution": false, "totalAcceptedRaw": 987127, "totalSubmissionRaw": 1510174}, "38": {"acRate": 62.21129187752794, "difficulty": "Medium", "likes": 5056, "dislikes": 9032, "categoryTitle": "Algorithms", "frontendQuestionId": "38", "paidOnly": false, "title": "Count and Say", "titleSlug": "count-and-say", "topicTags": [{"name": "String", "id": "VG9waWNUYWdOb2RlOjEw", "slug": "string"}], "hasSolution": true, "hasVideoSolution": false, "totalAcceptedRaw": 1366745, "totalSubmissionRaw": 2196941}, "39": {"acRate": 76.0077802177555, "difficulty": "Medium", "likes": 20777, "dislikes": 529, "categoryTitle": "Algorithms", "frontendQuestionId": "39", "paidOnly": false, "title": "Combination Sum", "titleSlug": "combination-sum", "topicTags": [{"name": "Array", "id": "VG9waWNUYWdOb2RlOjU=", "slug": "array"}, {"name": "Backtracking", "id": "VG9waWNUYWdOb2RlOjE0", "slug": "backtracking"}], "hasSolution": true, "hasVideoSolution": true, "totalAcceptedRaw": 2986676, "totalSubmissionRaw": 3929432}, "40": {"acRate": 58.89601741552406, "difficulty": "Medium", "likes": 12136, "dislikes": 380, "categoryTitle": "Algorithms", "frontendQuestionId": "40", "paidOnly": false, "title": "Combination Sum II", "titleSlug": "combination-sum-ii", "topicTags": [{"name": "Array", "id": "VG9waWNUYWdOb2RlOjU=", "slug": "array"}, {"name": "Backtracking", "id": "VG9waWNUYWdOb2RlOjE0", "slug": "backtracking"}], "hasSolution": true, "hasVideoSolution": false, "totalAcceptedRaw": 1626511, "totalSubmissionRaw": 2761665}, "41": {"acRate": 42.33377922545767, "difficulty": "Hard", "likes": 18231, "dislikes": 1976, "categoryTitle": "Algorithms", "frontendQuestionId": "41", "paidOnly": false, "title": "First Missing Positive", "titleSlug": "first-missing-positive", "topicTags": [{"name": "Array", "id": "VG9waWNUYWdOb2RlOjU=", "slug": "array"}, {"name": "Hash Table", "id": "VG9waWNUYWdOb2RlOjY=", "slug": "hash-table"}], "hasSolution": true, "hasVideoSolution": false, "totalAcceptedRaw": 1680467, "totalSubmissionRaw": 3969562}, "42": {"acRate": 66.68547354332868, "difficulty": "Hard", "likes": 35969, "dislikes": 684, "categoryTitle": "Algorithms", "frontendQuestionId": "42", "paidOnly": false, "title": "Trapping Rain Water", "titleSlug": "trapping-rain-water", "topicTags": [{"name": "Array", "id": "VG9waWNUYWdOb2RlOjU=", "slug": "array"}, {"name": "Two Pointers", "id": "VG9waWNUYWdOb2RlOjk=", "slug": "two-pointers"}, {"name": "Dynamic Programming", "id": "VG9waWNUYWdOb2RlOjEz", "slug": "dynamic-programming"}, {"name": "Stack", "id": "VG9waWNUYWdOb2RlOjE1", "slug": "stack"}, {"name": "Monotonic Stack", "id": "VG9waWNUYWdOb2RlOjYxMDU0", "slug": "monotonic-stack"}], "hasSolution": true, "hasVideoSolution": false, "totalAcceptedRaw": 3360236, "totalSubmissionRaw": 5038933}, "43": {"acRate": 43.48260806076482, "difficulty": "Medium", "likes": 7680, "dislikes": 3666, "categoryTitle": "Algorithms", "frontendQuestionId": "43", "paidOnly": false, "title": "Multiply Strings", "titleSlug": "multiply-strings", "topicTags": [{"name": "Math", "id": "VG9waWNUYWdOb2RlOjg=", "slug": "math"}, {"name": "String", "id": "VG9waWNUYWdOb2RlOjEw", "slug": "string"}, {"name": "Simulation", "id": "VG9waWNUYWdOb2RlOjYxMDU1", "slug": "simulation"}], "hasSolution": true, "hasVideoSolution": false, "totalAcceptedRaw": 1110703, "totalSubmissionRaw": 2554360}, "44": {"acRate": 31.27913929545073, "difficulty": "Hard", "likes": 9059, "dislikes": 412, "categoryTitle": "Algorithms", "frontendQuestionId": "44", "paidOnly": false, "title": "Wildcard Matching", "titleSlug": "wildcard-matching", "topicTags": [{"name": "String", "id": "VG9waWNUYWdOb2RlOjEw", "slug": "string"}, {"name": "Dynamic Programming", "id": "VG9waWNUYWdOb2RlOjEz", "slug": "dynamic-programming"}, {"name": "Greedy", "id": "VG9waWNUYWdOb2RlOjE3", "slug": "greedy"}, {"name": "Recursion", "id": "VG9waWNUYWdOb2RlOjMx", "slug": "recursion"}], "hasSolution": true, "hasVideoSolution": false, "totalAcceptedRaw": 833321, "totalSubmissionRaw": 2664143}, "45": {"acRate": 42.40518368852248, "difficulty": "Medium", "likes": 16323, "dislikes": 701, "categoryTitle": "Algorithms", "frontendQuestionId": "45", "paidOnly": false, "title": "Jump Game II", "titleSlug": "jump-game-ii", "topicTags": [{"name": "Array", "id": "VG9waWNUYWdOb2RlOjU=", "slug": "array"}, {"name": "Dynamic Programming", "id": "VG9waWNUYWdOb2RlOjEz", "slug": "dynamic-programming"}, {"name": "Greedy", "id": "VG9waWNUYWdOb2RlOjE3", "slug": "greedy"}], "hasSolution": true, "hasVideoSolution": false, "totalAcceptedRaw": 2037467, "totalSubmissionRaw": 4804762}, "46": {"acRate": 81.57138152895284, "difficulty": "Medium", "likes": 20700, "dislikes": 381, "categoryTitle": "Algorithms", "frontendQuestionId": "46", "paidOnly": false, "title": "Permutations", "titleSlug": "permutations", "topicTags": [{"name": "Array", "id": "VG9waWNUYWdOb2RlOjU=", "slug": "array"}, {"name": "Backtracking", "id": "VG9waWNUYWdOb2RlOjE0", "slug": "backtracking"}], "hasSolution": true, "hasVideoSolution": false, "totalAcceptedRaw": 2962653, "totalSubmissionRaw": 3631976}, "47": {"acRate": 62.89115666925918, "difficulty": "Medium", "likes": 9090, "dislikes": 162, "categoryTitle": "Algorithms", "frontendQuestionId": "47", "paidOnly": false, "title": "Permutations II", "titleSlug": "permutations-ii", "topicTags": [{"name": "Array", "id": "VG9waWNUYWdOb2RlOjU=", "slug": "array"}, {"name": "Backtracking", "id": "VG9waWNUYWdOb2RlOjE0", "slug": "backtracking"}, {"name": "Sorting", "id": "VG9waWNUYWdOb2RlOjYxMDQ5", "slug": "sorting"}], "hasSolution": true, "hasVideoSolution": false, "totalAcceptedRaw": 1242043, "totalSubmissionRaw": 1974908}, "48": {"acRate": 79.2500333908185, "difficulty": "Medium", "likes": 19673, "dislikes": 952, "categoryTitle": "Algorithms", "frontendQuestionId": "48", "paidOnly": false, "title": "Rotate Image", "titleSlug": "rotate-image", "topicTags": [{"name": "Array", "id": "VG9waWNUYWdOb2RlOjU=", "slug": "array"}, {"name": "Math", "id": "VG9waWNUYWdOb2RlOjg=", "slug": "math"}, {"name": "Matrix", "id": "VG9waWNUYWdOb2RlOjYxMDUz", "slug": "matrix"}], "hasSolution": true, "hasVideoSolution": false, "totalAcceptedRaw": 2693816, "totalSubmissionRaw": 3399136}, "49": {"acRate": 72.1075967497263, "difficulty": "Medium", "likes": 21786, "dislikes": 747, "categoryTitle": "Algorithms", "frontendQuestionId": "49", "paidOnly": false, "title": "Group Anagrams", "titleSlug": "group-anagrams", "topicTags": [{"name": "Array", "id": "VG9waWNUYWdOb2RlOjU=", "slug": "array"}, {"name": "Hash Table", "id": "VG9waWNUYWdOb2RlOjY=", "slug": "hash-table"}, {"name": "String", "id": "VG9waWNUYWdOb2RlOjEw", "slug": "string"}, {"name": "Sorting", "id": "VG9waWNUYWdOb2RlOjYxMDQ5", "slug": "sorting"}], "hasSolution": true, "hasVideoSolution": true, "totalAcceptedRaw": 4495762, "totalSubmissionRaw": 6234797}, "50": {"acRate": 38.18442561432528, "difficulty": "Medium", "likes": 11523, "dislikes": 10508, "categoryTitle": "Algorithms", "frontendQuestionId": "50", "paidOnly": false, "title": "Pow(x, n)", "titleSlug": "powx-n", "topicTags": [{"name": "Math", "id": "VG9waWNUYWdOb2RlOjg=", "slug": "math"}, {"name": "Recursion", "id": "VG9waWNUYWdOb2RlOjMx", "slug": "recursion"}], "hasSolution": true, "hasVideoSolution": false, "totalAcceptedRaw": 2594730, "totalSubmissionRaw": 6795259}, "51": {"acRate": 74.83227692378695, "difficulty": "Hard", "likes": 14138, "dislikes": 344, "categoryTitle": "Algorithms", "frontendQuestionId": "51", "paidOnly": false, "title": "N-Queens", "titleSlug": "n-queens", "topicTags": [{"name": "Array", "id": "VG9waWNUYWdOb2RlOjU=", "slug": "array"}, {"name": "Backtracking", "id": "VG9waWNUYWdOb2RlOjE0", "slug": "backtracking"}], "hasSolution": true, "hasVideoSolution": false, "totalAcceptedRaw": 1199844, "totalSubmissionRaw": 1603378}, "52": {"acRate": 78.0795926863726, "difficulty": "Hard", "likes": 4247, "dislikes": 282, "categoryTitle": "Algorithms", "frontendQuestionId": "52", "paidOnly": false, "title": "N-Queens II", "titleSlug": "n-queens-ii", "topicTags": [{"name": "Backtracking", "id": "VG9waWNUYWdOb2RlOjE0", "slug": "backtracking"}], "hasSolution": true, "hasVideoSolution": false, "totalAcceptedRaw": 572014, "totalSubmissionRaw": 732604}, "53": {"acRate": 52.90720958427261, "difficulty": "Medium", "likes": 37448, "dislikes": 1584, "categoryTitle": "Algorithms", "frontendQuestionId": "53", "paidOnly": false, "title": "Maximum Subarray", "titleSlug": "maximum-subarray", "topicTags": [{"name": "Array", "id": "VG9waWNUYWdOb2RlOjU=", "slug": "array"}, {"name": "Divide and Conquer", "id": "VG9waWNUYWdOb2RlOjEy", "slug": "divide-and-conquer"}, {"name": "Dynamic Programming", "id": "VG9waWNUYWdOb2RlOjEz", "slug": "dynamic-programming"}], "hasSolution": true, "hasVideoSolution": true, "totalAcceptedRaw": 5815378, "totalSubmissionRaw": 10991652}, "54": {"acRate": 56.00868588676303, "difficulty": "Medium", "likes": 17210, "dislikes": 1551, "categoryTitle": "Algorithms", "frontendQuestionId": "54", "paidOnly": false, "title": "Spiral Matrix", "titleSlug": "spiral-matrix", "topicTags": [{"name": "Array", "id": "VG9waWNUYWdOb2RlOjU=", "slug": "array"}, {"name": "Matrix", "id": "VG9waWNUYWdOb2RlOjYxMDUz", "slug": "matrix"}, {"name": "Simulation", "id": "VG9waWNUYWdOb2RlOjYxMDU1", "slug": "simulation"}], "hasSolution": true, "hasVideoSolution": false, "totalAcceptedRaw": 2275707, "totalSubmissionRaw": 4063132}, "55": {"acRate": 40.417578187548315, "difficulty": "Medium", "likes": 21551, "dislikes": 1476, "categoryTitle": "Algorithms", "frontendQuestionId": "55", "paidOnly": false, "title": "Jump Game", "titleSlug": "jump-game", "topicTags": [{"name": "Array", "id": "VG9waWNUYWdOb2RlOjU=", "slug": "array"}, {"name": "Dynamic Programming", "id": "VG9waWNUYWdOb2RlOjEz", "slug": "dynamic-programming"}, {"name": "Greedy", "id": "VG9waWNUYWdOb2RlOjE3", "slug": "greedy"}], "hasSolution": true, "hasVideoSolution": false, "totalAcceptedRaw": 3049162, "totalSubmissionRaw": 7544159}, "56": {"acRate": 51.06070762858966, "difficulty": "Medium", "likes": 24399, "dislikes": 898, "categoryTitle": "Algorithms", "frontendQuestionId": "56", "paidOnly": false, "title": "Merge Intervals", "titleSlug": "merge-intervals", "topicTags": [{"name": "Array", "id": "VG9waWNUYWdOb2RlOjU=", "slug": "array"}, {"name": "Sorting", "id": "VG9waWNUYWdOb2RlOjYxMDQ5", "slug": "sorting"}], "hasSolution": true, "hasVideoSolution": true, "totalAcceptedRaw": 3791757, "totalSubmissionRaw": 7425981}, "57": {"acRate": 44.684479788064976, "difficulty": "Medium", "likes": 11717, "dislikes": 913, "categoryTitle": "Algorithms", "frontendQuestionId": "57", "paidOnly": false, "title": "Insert Interval", "titleSlug": "insert-interval", "topicTags": [{"name": "Array", "id": "VG9waWNUYWdOb2RlOjU=", "slug": "array"}], "hasSolution": true, "hasVideoSolution": false, "totalAcceptedRaw": 1692796, "totalSubmissionRaw": 3788330}, "58": {"acRate": 58.16253200707935, "difficulty": "Easy", "likes": 6308, "dislikes": 351, "categoryTitle": "Algorithms", "frontendQuestionId": "58", "paidOnly": false, "title": "Length of Last Word", "titleSlug": "length-of-last-word", "topicTags": [{"name": "String", "id": "VG9waWNUYWdOb2RlOjEw", "slug": "string"}], "hasSolution": true, "hasVideoSolution": false, "totalAcceptedRaw": 3251144, "totalSubmissionRaw": 5589762}, "59": {"acRate": 74.5717477118989, "difficulty": "Medium", "likes": 6868, "dislikes": 287, "categoryTitle": "Algorithms", "frontendQuestionId": "59", "paidOnly": false, "title": "Spiral Matrix II", "titleSlug": "spiral-matrix-ii", "topicTags": [{"name": "Array", "id": "VG9waWNUYWdOb2RlOjU=", "slug": "array"}, {"name": "Matrix", "id": "VG9waWNUYWdOb2RlOjYxMDUz", "slug": "matrix"}, {"name": "Simulation", "id": "VG9waWNUYWdOb2RlOjYxMDU1", "slug": "simulation"}], "hasSolution": true, "hasVideoSolution": false, "totalAcceptedRaw": 775097, "totalSubmissionRaw": 1039398}, "60": {"acRate": 51.99875572702244, "difficulty": "Hard", "likes": 7196, "dislikes": 505, "categoryTitle": "Algorithms", "frontendQuestionId": "60", "paidOnly": false, "title": "Permutation Sequence", "titleSlug": "permutation-sequence", "topicTags": [{"name": "Math", "id": "VG9waWNUYWdOb2RlOjg=", "slug": "math"}, {"name": "Recursion", "id": "VG9waWNUYWdOb2RlOjMx", "slug": "recursion"}], "hasSolution": true, "hasVideoSolution": false, "totalAcceptedRaw": 548291, "totalSubmissionRaw": 1054431}, "61": {"acRate": 41.09989836391747, "difficulty": "Medium", "likes": 11122, "dislikes": 1540, "categoryTitle": "Algorithms", "frontendQuestionId": "61", "paidOnly": false, "title": "Rotate List", "titleSlug": "rotate-list", "topicTags": [{"name": "Linked List", "id": "VG9waWNUYWdOb2RlOjc=", "slug": "linked-list"}, {"name": "Two Pointers", "id": "VG9waWNUYWdOb2RlOjk=", "slug": "two-pointers"}], "hasSolution": true, "hasVideoSolution": false, "totalAcceptedRaw": 1526949, "totalSubmissionRaw": 3715214}, "62": {"acRate": 66.50550420633776, "difficulty": "Medium", "likes": 18219, "dislikes": 491, "categoryTitle": "Algorithms", "frontendQuestionId": "62", "paidOnly": false, "title": "Unique Paths", "titleSlug": "unique-paths", "topicTags": [{"name": "Math", "id": "VG9waWNUYWdOb2RlOjg=", "slug": "math"}, {"name": "Dynamic Programming", "id": "VG9waWNUYWdOb2RlOjEz", "slug": "dynamic-programming"}, {"name": "Combinatorics", "id": "VG9waWNUYWdOb2RlOjYxMDU2", "slug": "combinatorics"}], "hasSolution": true, "hasVideoSolution": false, "totalAcceptedRaw": 2706083, "totalSubmissionRaw": 4068967}, "63": {"acRate": 44.08214296916269, "difficulty": "Medium", "likes": 9610, "dislikes": 557, "categoryTitle": "Algorithms", "frontendQuestionId": "63", "paidOnly": false, "title": "Unique Paths II", "titleSlug": "unique-paths-ii", "topicTags": [{"name": "Array", "id": "VG9waWNUYWdOb2RlOjU=", "slug": "array"}, {"name": "Dynamic Programming", "id": "VG9waWNUYWdOb2RlOjEz", "slug": "dynamic-programming"}, {"name": "Matrix", "id": "VG9waWNUYWdOb2RlOjYxMDUz", "slug": "matrix"}], "hasSolution": true, "hasVideoSolution": false, "totalAcceptedRaw": 1419486, "totalSubmissionRaw": 3220093}, "64": {"acRate": 67.74518175281494, "difficulty": "Medium", "likes": 13579, "dislikes": 197, "categoryTitle": "Algorithms", "frontendQuestionId": "64", "paidOnly": false, "title": "Minimum Path Sum", "titleSlug": "minimum-path-sum", "topicTags": [{"name": "Array", "id": "VG9waWNUYWdOb2RlOjU=", "slug": "array"}, {"name": "Dynamic Programming", "id": "VG9waWNUYWdOb2RlOjEz", "slug": "dynamic-programming"}, {"name": "Matrix", "id": "VG9waWNUYWdOb2RlOjYxMDUz", "slug": "matrix"}], "hasSolution": true, "hasVideoSolution": false, "totalAcceptedRaw": 1768450, "totalSubmissionRaw": 2610443}, "65": {"acRate": 22.52870283508774, "difficulty": "Hard", "likes": 1484, "dislikes": 2205, "categoryTitle": "Algorithms", "frontendQuestionId": "65", "paidOnly": false, "title": "Valid Number", "titleSlug": "valid-number", "topicTags": [{"name": "String", "id": "VG9waWNUYWdOb2RlOjEw", "slug": "string"}], "hasSolution": true, "hasVideoSolution": false, "totalAcceptedRaw": 502156, "totalSubmissionRaw": 2228961}, "66": {"acRate": 49.441681285984615, "difficulty": "Easy", "likes": 11646, "dislikes": 5591, "categoryTitle": "Algorithms", "frontendQuestionId": "66", "paidOnly": false, "title": "Plus One", "titleSlug": "plus-one", "topicTags": [{"name": "Array", "id": "VG9waWNUYWdOb2RlOjU=", "slug": "array"}, {"name": "Math", "id": "VG9waWNUYWdOb2RlOjg=", "slug": "math"}], "hasSolution": true, "hasVideoSolution": false, "totalAcceptedRaw": 3568785, "totalSubmissionRaw": 7218174}, "67": {"acRate": 56.82160794042037, "difficulty": "Easy", "likes": 10411, "dislikes": 1095, "categoryTitle": "Algorithms", "frontendQuestionId": "67", "paidOnly": false, "title": "Add Binary", "titleSlug": "add-binary", "topicTags": [{"name": "Math", "id": "VG9waWNUYWdOb2RlOjg=", "slug": "math"}, {"name": "String", "id": "VG9waWNUYWdOb2RlOjEw", "slug": "string"}, {"name": "Bit Manipulation", "id": "VG9waWNUYWdOb2RlOjE5", "slug": "bit-manipulation"}, {"name": "Simulation", "id": "VG9waWNUYWdOb2RlOjYxMDU1", "slug": "simulation"}], "hasSolution": true, "hasVideoSolution": false, "totalAcceptedRaw": 2146220, "totalSubmissionRaw": 3777122}, "68": {"acRate": 50.29805089922282, "difficulty": "Hard", "likes": 4495, "dislikes": 5343, "categoryTitle": "Algorithms", "frontendQuestionId": "68", "paidOnly": false, "title": "Text Justification", "titleSlug": "text-justification", "topicTags": [{"name": "Array", "id": "VG9waWNUYWdOb2RlOjU=", "slug": "array"}, {"name": "String", "id": "VG9waWNUYWdOb2RlOjEw", "slug": "string"}, {"name": "Simulation", "id": "VG9waWNUYWdOb2RlOjYxMDU1", "slug": "simulation"}], "hasSolution": true, "hasVideoSolution": false, "totalAcceptedRaw": 624988, "totalSubmissionRaw": 1242571}, "69": {"acRate": 41.34571503408281, "difficulty": "Easy", "likes": 9544, "dislikes": 4633, "categoryTitle": "Algorithms", "frontendQuestionId": "69", "paidOnly": false, "title": "Sqrt(x)", "titleSlug": "sqrtx", "topicTags": [{"name": "Math", "id": "VG9waWNUYWdOb2RlOjg=", "slug": "math"}, {"name": "Binary Search", "id": "VG9waWNUYWdOb2RlOjEx", "slug": "binary-search"}], "hasSolution": true, "hasVideoSolution": true, "totalAcceptedRaw": 3032315, "totalSubmissionRaw": 7334047}, "70": {"acRate": 53.8813978582089, "difficulty": "Easy", "likes": 24232, "dislikes": 1033, "categoryTitle": "Algorithms", "frontendQuestionId": "70", "paidOnly": false, "title": "Climbing Stairs", "titleSlug": "climbing-stairs", "topicTags": [{"name": "Math", "id": "VG9waWNUYWdOb2RlOjg=", "slug": "math"}, {"name": "Dynamic Programming", "id": "VG9waWNUYWdOb2RlOjEz", "slug": "dynamic-programming"}, {"name": "Memoization", "id": "VG9waWNUYWdOb2RlOjMz", "slug": "memoization"}], "hasSolution": true, "hasVideoSolution": false, "totalAcceptedRaw": 4895132, "totalSubmissionRaw": 9085013}, "71": {"acRate": 49.89665378094056, "difficulty": "Medium", "likes": 6474, "dislikes": 1401, "categoryTitle": "Algorithms", "frontendQuestionId": "71", "paidOnly": false, "title": "Simplify Path", "titleSlug": "simplify-path", "topicTags": [{"name": "String", "id": "VG9waWNUYWdOb2RlOjEw", "slug": "string"}, {"name": "Stack", "id": "VG9waWNUYWdOb2RlOjE1", "slug": "stack"}], "hasSolution": true, "hasVideoSolution": true, "totalAcceptedRaw": 1270998, "totalSubmissionRaw": 2547259}, "72": {"acRate": 60.05925576636646, "difficulty": "Medium", "likes": 16285, "dislikes": 320, "categoryTitle": "Algorithms", "frontendQuestionId": "72", "paidOnly": false, "title": "Edit Distance", "titleSlug": "edit-distance", "topicTags": [{"name": "String", "id": "VG9waWNUYWdOb2RlOjEw", "slug": "string"}, {"name": "Dynamic Programming", "id": "VG9waWNUYWdOb2RlOjEz", "slug": "dynamic-programming"}], "hasSolution": true, "hasVideoSolution": false, "totalAcceptedRaw": 1380668, "totalSubmissionRaw": 2298845}, "73": {"acRate": 62.33843054447371, "difficulty": "Medium", "likes": 16928, "dislikes": 855, "categoryTitle": "Algorithms", "frontendQuestionId": "73", "paidOnly": false, "title": "Set Matrix Zeroes", "titleSlug": "set-matrix-zeroes", "topicTags": [{"name": "Array", "id": "VG9waWNUYWdOb2RlOjU=", "slug": "array"}, {"name": "Hash Table", "id": "VG9waWNUYWdOb2RlOjY=", "slug": "hash-table"}, {"name": "Matrix", "id": "VG9waWNUYWdOb2RlOjYxMDUz", "slug": "matrix"}], "hasSolution": true, "hasVideoSolution": false, "totalAcceptedRaw": 2461840, "totalSubmissionRaw": 3949153}, "74": {"acRate": 53.45086902280458, "difficulty": "Medium", "likes": 17715, "dislikes": 480, "categoryTitle": "Algorithms", "frontendQuestionId": "74", "paidOnly": false, "title": "Search a 2D Matrix", "titleSlug": "search-a-2d-matrix", "topicTags": [{"name": "Array", "id": "VG9waWNUYWdOb2RlOjU=", "slug": "array"}, {"name": "Binary Search", "id": "VG9waWNUYWdOb2RlOjEx", "slug": "binary-search"}, {"name": "Matrix", "id": "VG9waWNUYWdOb2RlOjYxMDUz", "slug": "matrix"}], "hasSolution": true, "hasVideoSolution": false, "totalAcceptedRaw": 2759189, "totalSubmissionRaw": 5162109}, "75": {"acRate": 69.06719440594284, "difficulty": "Medium", "likes": 21323, "dislikes": 761, "categoryTitle": "Algorithms", "frontendQuestionId": "75", "paidOnly": false, "title": "Sort Colors", "titleSlug": "sort-colors", "topicTags": [{"name": "Array", "id": "VG9waWNUYWdOb2RlOjU=", "slug": "array"}, {"name": "Two Pointers", "id": "VG9waWNUYWdOb2RlOjk=", "slug": "two-pointers"}, {"name": "Sorting", "id": "VG9waWNUYWdOb2RlOjYxMDQ5", "slug": "sorting"}], "hasSolution": true, "hasVideoSolution": false, "totalAcceptedRaw": 3537416, "totalSubmissionRaw": 5121700}, "76": {"acRate": 46.84941457018991, "difficulty": "Hard", "likes": 19944, "dislikes": 846, "categoryTitle": "Algorithms", "frontendQuestionId": "76", "paidOnly": false, "title": "Minimum Window Substring", "titleSlug": "minimum-window-substring", "topicTags": [{"name": "Hash Table", "id": "VG9waWNUYWdOb2RlOjY=", "slug": "hash-table"}, {"name": "String", "id": "VG9waWNUYWdOb2RlOjEw", "slug": "string"}, {"name": "Sliding Window", "id": "VG9waWNUYWdOb2RlOjU1ODIx", "slug": "sliding-window"}], "hasSolution": true, "hasVideoSolution": false, "totalAcceptedRaw": 2051062, "totalSubmissionRaw": 4377986}, "77": {"acRate": 74.1126560849623, "difficulty": "Medium", "likes": 8857, "dislikes": 252, "categoryTitle": "Algorithms", "frontendQuestionId": "77", "paidOnly": false, "title": "Combinations", "titleSlug": "combinations", "topicTags": [{"name": "Backtracking", "id": "VG9waWNUYWdOb2RlOjE0", "slug": "backtracking"}], "hasSolution": true, "hasVideoSolution": false, "totalAcceptedRaw": 1280536, "totalSubmissionRaw": 1727824}, "78": {"acRate": 81.97721491495822, "difficulty": "Medium", "likes": 19032, "dislikes": 338, "categoryTitle": "Algorithms", "frontendQuestionId": "78", "paidOnly": false, "title": "Subsets", "titleSlug": "subsets", "topicTags": [{"name": "Array", "id": "VG9waWNUYWdOb2RlOjU=", "slug": "array"}, {"name": "Backtracking", "id": "VG9waWNUYWdOb2RlOjE0", "slug": "backtracking"}, {"name": "Bit Manipulation", "id": "VG9waWNUYWdOb2RlOjE5", "slug": "bit-manipulation"}], "hasSolution": true, "hasVideoSolution": true, "totalAcceptedRaw": 2913953, "totalSubmissionRaw": 3554592}, "79": {"acRate": 46.755621185295695, "difficulty": "Medium", "likes": 17515, "dislikes": 751, "categoryTitle": "Algorithms", "frontendQuestionId": "79", "paidOnly": false, "title": "Word Search", "titleSlug": "word-search", "topicTags": [{"name": "Array", "id": "VG9waWNUYWdOb2RlOjU=", "slug": "array"}, {"name": "String", "id": "VG9waWNUYWdOb2RlOjEw", "slug": "string"}, {"name": "Backtracking", "id": "VG9waWNUYWdOb2RlOjE0", "slug": "backtracking"}, {"name": "Depth-First Search", "id": "VG9waWNUYWdOb2RlOjIx", "slug": "depth-first-search"}, {"name": "Matrix", "id": "VG9waWNUYWdOb2RlOjYxMDUz", "slug": "matrix"}], "hasSolution": true, "hasVideoSolution": false, "totalAcceptedRaw": 2401308, "totalSubmissionRaw": 5135876}, "80": {"acRate": 64.20564433040911, "difficulty": "Medium", "likes": 8150, "dislikes": 1510, "categoryTitle": "Algorithms", "frontendQuestionId": "80", "paidOnly": false, "title": "Remove Duplicates from Sorted Array II", "titleSlug": "remove-duplicates-from-sorted-array-ii", "topicTags": [{"name": "Array", "id": "VG9waWNUYWdOb2RlOjU=", "slug": "array"}, {"name": "Two Pointers", "id": "VG9waWNUYWdOb2RlOjk=", "slug": "two-pointers"}], "hasSolution": true, "hasVideoSolution": false, "totalAcceptedRaw": 1841482, "totalSubmissionRaw": 2868105}, "81": {"acRate": 39.674145198050184, "difficulty": "Medium", "likes": 9534, "dislikes": 1116, "categoryTitle": "Algorithms", "frontendQuestionId": "81", "paidOnly": false, "title": "Search in Rotated Sorted Array II", "titleSlug": "search-in-rotated-sorted-array-ii", "topicTags": [{"name": "Array", "id": "VG9waWNUYWdOb2RlOjU=", "slug": "array"}, {"name": "Binary Search", "id": "VG9waWNUYWdOb2RlOjEx", "slug": "binary-search"}], "hasSolution": true, "hasVideoSolution": false, "totalAcceptedRaw": 1173977, "totalSubmissionRaw": 2959052}, "82": {"acRate": 51.2398698647181, "difficulty": "Medium", "likes": 9598, "dislikes": 280, "categoryTitle": "Algorithms", "frontendQuestionId": "82", "paidOnly": false, "title": "Remove Duplicates from Sorted List II", "titleSlug": "remove-duplicates-from-sorted-list-ii", "topicTags": [{"name": "Linked List", "id": "VG9waWNUYWdOb2RlOjc=", "slug": "linked-list"}, {"name": "Two Pointers", "id": "VG9waWNUYWdOb2RlOjk=", "slug": "two-pointers"}], "hasSolution": true, "hasVideoSolution": false, "totalAcceptedRaw": 1056327, "totalSubmissionRaw": 2061537}, "83": {"acRate": 56.17575263634911, "difficulty": "Easy", "likes": 9752, "dislikes": 359, "categoryTitle": "Algorithms", "frontendQuestionId": "83", "paidOnly": false, "title": "Remove Duplicates from Sorted List", "titleSlug": "remove-duplicates-from-sorted-list", "topicTags": [{"name": "Linked List", "id": "VG9waWNUYWdOb2RlOjc=", "slug": "linked-list"}], "hasSolution": true, "hasVideoSolution": true, "totalAcceptedRaw": 2263554, "totalSubmissionRaw": 4029420}, "84": {"acRate": 49.247346754698796, "difficulty": "Hard", "likes": 19386, "dislikes": 380, "categoryTitle": "Algorithms", "frontendQuestionId": "84", "paidOnly": false, "title": "Largest Rectangle in Histogram", "titleSlug": "largest-rectangle-in-histogram", "topicTags": [{"name": "Array", "id": "VG9waWNUYWdOb2RlOjU=", "slug": "array"}, {"name": "Stack", "id": "VG9waWNUYWdOb2RlOjE1", "slug": "stack"}, {"name": "Monotonic Stack", "id": "VG9waWNUYWdOb2RlOjYxMDU0", "slug": "monotonic-stack"}], "hasSolution": true, "hasVideoSolution": true, "totalAcceptedRaw": 1467629, "totalSubmissionRaw": 2980119}, "85": {"acRate": 57.993857643445665, "difficulty": "Hard", "likes": 11991, "dislikes": 226, "categoryTitle": "Algorithms", "frontendQuestionId": "85", "paidOnly": false, "title": "Maximal Rectangle", "titleSlug": "maximal-rectangle", "topicTags": [{"name": "Array", "id": "VG9waWNUYWdOb2RlOjU=", "slug": "array"}, {"name": "Dynamic Programming", "id": "VG9waWNUYWdOb2RlOjEz", "slug": "dynamic-programming"}, {"name": "Stack", "id": "VG9waWNUYWdOb2RlOjE1", "slug": "stack"}, {"name": "Matrix", "id": "VG9waWNUYWdOb2RlOjYxMDUz", "slug": "matrix"}, {"name": "Monotonic Stack", "id": "VG9waWNUYWdOb2RlOjYxMDU0", "slug": "monotonic-stack"}], "hasSolution": true, "hasVideoSolution": false, "totalAcceptedRaw": 771570, "totalSubmissionRaw": 1330434}, "86": {"acRate": 60.4998106304964, "difficulty": "Medium", "likes": 7979, "dislikes": 982, "categoryTitle": "Algorithms", "frontendQuestionId": "86", "paidOnly": false, "title": "Partition List", "titleSlug": "partition-list", "topicTags": [{"name": "Linked List", "id": "VG9waWNUYWdOb2RlOjc=", "slug": "linked-list"}, {"name": "Two Pointers", "id": "VG9waWNUYWdOb2RlOjk=", "slug": "two-pointers"}], "hasSolution": true, "hasVideoSolution": false, "totalAcceptedRaw": 872181, "totalSubmissionRaw": 1441626}, "87": {"acRate": 43.782660924848976, "difficulty": "Hard", "likes": 3609, "dislikes": 1309, "categoryTitle": "Algorithms", "frontendQuestionId": "87", "paidOnly": false, "title": "Scramble String", "titleSlug": "scramble-string", "topicTags": [{"name": "String", "id": "VG9waWNUYWdOb2RlOjEw", "slug": "string"}, {"name": "Dynamic Programming", "id": "VG9waWNUYWdOb2RlOjEz", "slug": "dynamic-programming"}], "hasSolution": true, "hasVideoSolution": false, "totalAcceptedRaw": 302874, "totalSubmissionRaw": 691767}, "88": {"acRate": 54.294618411334504, "difficulty": "Easy", "likes": 18624, "dislikes": 2606, "categoryTitle": "Algorithms", "frontendQuestionId": "88", "paidOnly": false, "title": "Merge Sorted Array", "titleSlug": "merge-sorted-array", "topicTags": [{"name": "Array", "id": "VG9waWNUYWdOb2RlOjU=", "slug": "array"}, {"name": "Two Pointers", "id": "VG9waWNUYWdOb2RlOjk=", "slug": "two-pointers"}, {"name": "Sorting", "id": "VG9waWNUYWdOb2RlOjYxMDQ5", "slug": "sorting"}], "hasSolution": true, "hasVideoSolution": true, "totalAcceptedRaw": 5414913, "totalSubmissionRaw": 9973202}, "89": {"acRate": 63.959171686866526, "difficulty": "Medium", "likes": 2509, "dislikes": 2832, "categoryTitle": "Algorithms", "frontendQuestionId": "89", "paidOnly": false, "title": "Gray Code", "titleSlug": "gray-code", "topicTags": [{"name": "Math", "id": "VG9waWNUYWdOb2RlOjg=", "slug": "math"}, {"name": "Backtracking", "id": "VG9waWNUYWdOb2RlOjE0", "slug": "backtracking"}, {"name": "Bit Manipulation", "id": "VG9waWNUYWdOb2RlOjE5", "slug": "bit-manipulation"}], "hasSolution": true, "hasVideoSolution": false, "totalAcceptedRaw": 402913, "totalSubmissionRaw": 629954}, "90": {"acRate": 60.79924096957101, "difficulty": "Medium", "likes": 10831, "dislikes": 407, "categoryTitle": "Algorithms", "frontendQuestionId": "90", "paidOnly": false, "title": "Subsets II", "titleSlug": "subsets-ii", "topicTags": [{"name": "Array", "id": "VG9waWNUYWdOb2RlOjU=", "slug": "array"}, {"name": "Backtracking", "id": "VG9waWNUYWdOb2RlOjE0", "slug": "backtracking"}, {"name": "Bit Manipulation", "id": "VG9waWNUYWdOb2RlOjE5", "slug": "bit-manipulation"}], "hasSolution": true, "hasVideoSolution": false, "totalAcceptedRaw": 1426439, "totalSubmissionRaw": 2346148}, "91": {"acRate": 37.56065327744692, "difficulty": "Medium", "likes": 12796, "dislikes": 4608, "categoryTitle": "Algorithms", "frontendQuestionId": "91", "paidOnly": false, "title": "Decode Ways", "titleSlug": "decode-ways", "topicTags": [{"name": "String", "id": "VG9waWNUYWdOb2RlOjEw", "slug": "string"}, {"name": "Dynamic Programming", "id": "VG9waWNUYWdOb2RlOjEz", "slug": "dynamic-programming"}], "hasSolution": true, "hasVideoSolution": true, "totalAcceptedRaw": 1609785, "totalSubmissionRaw": 4285829}, "92": {"acRate": 50.90898564150069, "difficulty": "Medium", "likes": 12820, "dislikes": 779, "categoryTitle": "Algorithms", "frontendQuestionId": "92", "paidOnly": false, "title": "Reverse Linked List II", "titleSlug": "reverse-linked-list-ii", "topicTags": [{"name": "Linked List", "id": "VG9waWNUYWdOb2RlOjc=", "slug": "linked-list"}], "hasSolution": true, "hasVideoSolution": true, "totalAcceptedRaw": 1257397, "totalSubmissionRaw": 2469893}, "93": {"acRate": 55.1801286986225, "difficulty": "Medium", "likes": 5614, "dislikes": 820, "categoryTitle": "Algorithms", "frontendQuestionId": "93", "paidOnly": false, "title": "Restore IP Addresses", "titleSlug": "restore-ip-addresses", "topicTags": [{"name": "String", "id": "VG9waWNUYWdOb2RlOjEw", "slug": "string"}, {"name": "Backtracking", "id": "VG9waWNUYWdOb2RlOjE0", "slug": "backtracking"}], "hasSolution": true, "hasVideoSolution": false, "totalAcceptedRaw": 603513, "totalSubmissionRaw": 1093716}, "94": {"acRate": 79.65564769759136, "difficulty": "Easy", "likes": 14778, "dislikes": 890, "categoryTitle": "Algorithms", "frontendQuestionId": "94", "paidOnly": false, "title": "Binary Tree Inorder Traversal", "titleSlug": "binary-tree-inorder-traversal", "topicTags": [{"name": "Stack", "id": "VG9waWNUYWdOb2RlOjE1", "slug": "stack"}, {"name": "Tree", "id": "VG9waWNUYWdOb2RlOjIw", "slug": "tree"}, {"name": "Depth-First Search", "id": "VG9waWNUYWdOb2RlOjIx", "slug": "depth-first-search"}, {"name": "Binary Tree", "id": "VG9waWNUYWdOb2RlOjYxMDU3", "slug": "binary-tree"}], "hasSolution": true, "hasVideoSolution": false, "totalAcceptedRaw": 3556502, "totalSubmissionRaw": 4464846}, "95": {"acRate": 61.809438838093754, "difficulty": "Medium", "likes": 7926, "dislikes": 581, "categoryTitle": "Algorithms", "frontendQuestionId": "95", "paidOnly": false, "title": "Unique Binary Search Trees II", "titleSlug": "unique-binary-search-trees-ii", "topicTags": [{"name": "Dynamic Programming", "id": "VG9waWNUYWdOb2RlOjEz", "slug": "dynamic-programming"}, {"name": "Backtracking", "id": "VG9waWNUYWdOb2RlOjE0", "slug": "backtracking"}, {"name": "Tree", "id": "VG9waWNUYWdOb2RlOjIw", "slug": "tree"}, {"name": "Binary Search Tree", "id": "VG9waWNUYWdOb2RlOjMw", "slug": "binary-search-tree"}, {"name": "Binary Tree", "id": "VG9waWNUYWdOb2RlOjYxMDU3", "slug": "binary-tree"}], "hasSolution": true, "hasVideoSolution": false, "totalAcceptedRaw": 561839, "totalSubmissionRaw": 908987}, "96": {"acRate": 63.24998376699369, "difficulty": "Medium", "likes": 10960, "dislikes": 445, "categoryTitle": "Algorithms", "frontendQuestionId": "96", "paidOnly": false, "title": "Unique Binary Search Trees", "titleSlug": "unique-binary-search-trees", "topicTags": [{"name": "Math", "id": "VG9waWNUYWdOb2RlOjg=", "slug": "math"}, {"name": "Dynamic Programming", "id": "VG9waWNUYWdOb2RlOjEz", "slug": "dynamic-programming"}, {"name": "Tree", "id": "VG9waWNUYWdOb2RlOjIw", "slug": "tree"}, {"name": "Binary Search Tree", "id": "VG9waWNUYWdOb2RlOjMw", "slug": "binary-search-tree"}, {"name": "Binary Tree", "id": "VG9waWNUYWdOb2RlOjYxMDU3", "slug": "binary-tree"}], "hasSolution": true, "hasVideoSolution": false, "totalAcceptedRaw": 837718, "totalSubmissionRaw": 1324458}, "97": {"acRate": 43.43913135229195, "difficulty": "Medium", "likes": 8801, "dislikes": 550, "categoryTitle": "Algorithms", "frontendQuestionId": "97", "paidOnly": false, "title": "Interleaving String", "titleSlug": "interleaving-string", "topicTags": [{"name": "String", "id": "VG9waWNUYWdOb2RlOjEw", "slug": "string"}, {"name": "Dynamic Programming", "id": "VG9waWNUYWdOb2RlOjEz", "slug": "dynamic-programming"}], "hasSolution": true, "hasVideoSolution": false, "totalAcceptedRaw": 753392, "totalSubmissionRaw": 1734366}, "98": {"acRate": 35.29484219914292, "difficulty": "Medium", "likes": 18241, "dislikes": 1444, "categoryTitle": "Algorithms", "frontendQuestionId": "98", "paidOnly": false, "title": "Validate Binary Search Tree", "titleSlug": "validate-binary-search-tree", "topicTags": [{"name": "Tree", "id": "VG9waWNUYWdOb2RlOjIw", "slug": "tree"}, {"name": "Depth-First Search", "id": "VG9waWNUYWdOb2RlOjIx", "slug": "depth-first-search"}, {"name": "Binary Search Tree", "id": "VG9waWNUYWdOb2RlOjMw", "slug": "binary-search-tree"}, {"name": "Binary Tree", "id": "VG9waWNUYWdOb2RlOjYxMDU3", "slug": "binary-tree"}], "hasSolution": true, "hasVideoSolution": true, "totalAcceptedRaw": 3215033, "totalSubmissionRaw": 9109073}, "99": {"acRate": 58.62914920335851, "difficulty": "Medium", "likes": 8542, "dislikes": 288, "categoryTitle": "Algorithms", "frontendQuestionId": "99", "paidOnly": false, "title": "Recover Binary Search Tree", "titleSlug": "recover-binary-search-tree", "topicTags": [{"name": "Tree", "id": "VG9waWNUYWdOb2RlOjIw", "slug": "tree"}, {"name": "Depth-First Search", "id": "VG9waWNUYWdOb2RlOjIx", "slug": "depth-first-search"}, {"name": "Binary Search Tree", "id": "VG9waWNUYWdOb2RlOjMw", "slug": "binary-search-tree"}, {"name": "Binary Tree", "id": "VG9waWNUYWdOb2RlOjYxMDU3", "slug": "binary-tree"}], "hasSolution": true, "hasVideoSolution": false, "totalAcceptedRaw": 633541, "totalSubmissionRaw": 1080589}, "100": {"acRate": 66.54373412294166, "difficulty": "Easy", "likes": 12767, "dislikes": 295, "categoryTitle": "Algorithms", "frontendQuestionId": "100", "paidOnly": false, "title": "Same Tree", "titleSlug": "same-tree", "topicTags": [{"name": "Tree", "id": "VG9waWNUYWdOb2RlOjIw", "slug": "tree"}, {"name": "Depth-First Search", "id": "VG9waWNUYWdOb2RlOjIx", "slug": "depth-first-search"}, {"name": "Breadth-First Search", "id": "VG9waWNUYWdOb2RlOjIy", "slug": "breadth-first-search"}, {"name": "Binary Tree", "id": "VG9waWNUYWdOb2RlOjYxMDU3", "slug": "binary-tree"}], "hasSolution": true, "hasVideoSolution": true, "totalAcceptedRaw": 3261529, "totalSubmissionRaw": 4901331}}