{"1": {"acRate": 56.85213160639363, "difficulty": "Easy", "likes": 66763, "dislikes": 2484, "categoryTitle": "Algorithms", "frontendQuestionId": "1", "paidOnly": false, "title": "Two Sum", "titleSlug": "two-sum", "topicTags": [{"name": "Array", "id": "VG9waWNUYWdOb2RlOjU=", "slug": "array"}, {"name": "Hash Table", "id": "VG9waWNUYWdOb2RlOjY=", "slug": "hash-table"}], "hasSolution": true, "hasVideoSolution": true, "totalAcceptedRaw": 20250530, "totalSubmissionRaw": 35619686}, "2": {"acRate": 47.66956571339841, "difficulty": "Medium", "likes": 35935, "dislikes": 7123, "categoryTitle": "Algorithms", "frontendQuestionId": "2", "paidOnly": false, "title": "Add Two Numbers", "titleSlug": "add-two-numbers", "topicTags": [{"name": "Linked List", "id": "VG9waWNUYWdOb2RlOjc=", "slug": "linked-list"}, {"name": "Math", "id": "VG9waWNUYWdOb2RlOjg=", "slug": "math"}, {"name": "Recursion", "id": "VG9waWNUYWdOb2RlOjMx", "slug": "recursion"}], "hasSolution": true, "hasVideoSolution": true, "totalAcceptedRaw": 6618813, "totalSubmissionRaw": 13884783}, "3": {"acRate": 38.227355416654554, "difficulty": "Medium", "likes": 44102, "dislikes": 2160, "categoryTitle": "Algorithms", "frontendQuestionId": "3", "paidOnly": false, "title": "Longest Substring Without Repeating Characters", "titleSlug": "longest-substring-without-repeating-characters", "topicTags": [{"name": "Hash Table", "id": "VG9waWNUYWdOb2RlOjY=", "slug": "hash-table"}, {"name": "String", "id": "VG9waWNUYWdOb2RlOjEw", "slug": "string"}, {"name": "Sliding Window", "id": "VG9waWNUYWdOb2RlOjU1ODIx", "slug": "sliding-window"}], "hasSolution": true, "hasVideoSolution": true, "totalAcceptedRaw": 8784542, "totalSubmissionRaw": 22979738}, "4": {"acRate": 45.60253794459096, "difficulty": "Hard", "likes": 31578, "dislikes": 3536, "categoryTitle": "Algorithms", "frontendQuestionId": "4", "paidOnly": false, "title": "Median of Two Sorted Arrays", "titleSlug": "median-of-two-sorted-arrays", "topicTags": [{"name": "Array", "id": "VG9waWNUYWdOb2RlOjU=", "slug": "array"}, {"name": "Binary Search", "id": "VG9waWNUYWdOb2RlOjEx", "slug": "binary-search"}, {"name": "Divide and Conquer", "id": "VG9waWNUYWdOb2RlOjEy", "slug": "divide-and-conquer"}], "hasSolution": true, "hasVideoSolution": true, "totalAcceptedRaw": 3971702, "totalSubmissionRaw": 8709386}, "5": {"acRate": 37.06365303517805, "difficulty": "Medium", "likes": 32118, "dislikes": 1976, "categoryTitle": "Algorithms", "frontendQuestionId": "5", "paidOnly": false, "title": "Longest Palindromic Substring", "titleSlug": "longest-palindromic-substring", "topicTags": [{"name": "Two Pointers", "id": "VG9waWNUYWdOb2RlOjk=", "slug": "two-pointers"}, {"name": "String", "id": "VG9waWNUYWdOb2RlOjEw", "slug": "string"}, {"name": "Dynamic Programming", "id": "VG9waWNUYWdOb2RlOjEz", "slug": "dynamic-programming"}], "hasSolution": true, "hasVideoSolution": true, "totalAcceptedRaw": 4442861, "totalSubmissionRaw": 11987162}, "6": {"acRate": 53.23324200063817, "difficulty": "Medium", "likes": 9137, "dislikes": 15787, "categoryTitle": "Algorithms", "frontendQuestionId": "6", "paidOnly": false, "title": "Zigzag Conversion", "titleSlug": "zigzag-conversion", "topicTags": [{"name": "String", "id": "VG9waWNUYWdOb2RlOjEw", "slug": "string"}], "hasSolution": true, "hasVideoSolution": true, "totalAcceptedRaw": 2060374, "totalSubmissionRaw": 3870465}, "7": {"acRate": 31.30950722485755, "difficulty": "Medium", "likes": 15148, "dislikes": 13946, "categoryTitle": "Algorithms", "frontendQuestionId": "7", "paidOnly": false, "title": "Reverse Integer", "titleSlug": "reverse-integer", "topicTags": [{"name": "Math", "id": "VG9waWNUYWdOb2RlOjg=", "slug": "math"}], "hasSolution": true, "hasVideoSolution": true, "totalAcceptedRaw": 4690415, "totalSubmissionRaw": 14980814}, "8": {"acRate": 20.36434436598498, "difficulty": "Medium", "likes": 6003, "dislikes": 15393, "categoryTitle": "Algorithms", "frontendQuestionId": "8", "paidOnly": false, "title": "String to Integer (atoi)", "titleSlug": "string-to-integer-atoi", "topicTags": [{"name": "String", "id": "VG9waWNUYWdOb2RlOjEw", "slug": "string"}], "hasSolution": true, "hasVideoSolution": false, "totalAcceptedRaw": 2292370, "totalSubmissionRaw": 11256772}, "9": {"acRate": 60.09315767816679, "difficulty": "Easy", "likes": 15413, "dislikes": 2901, "categoryTitle": "Algorithms", "frontendQuestionId": "9", "paidOnly": false, "title": "Palindrome Number", "titleSlug": "palindrome-number", "topicTags": [{"name": "Math", "id": "VG9waWNUYWdOb2RlOjg=", "slug": "math"}], "hasSolution": true, "hasVideoSolution": true, "totalAcceptedRaw": 7559055, "totalSubmissionRaw": 12578894}, "10": {"acRate": 30.222658604353143, "difficulty": "Hard", "likes": 13173, "dislikes": 2375, "categoryTitle": "Algorithms", "frontendQuestionId": "10", "paidOnly": false, "title": "Regular Expression Matching", "titleSlug": "regular-expression-matching", "topicTags": [{"name": "String", "id": "VG9waWNUYWdOb2RlOjEw", "slug": "string"}, {"name": "Dynamic Programming", "id": "VG9waWNUYWdOb2RlOjEz", "slug": "dynamic-programming"}, {"name": "Recursion", "id": "VG9waWNUYWdOb2RlOjMx", "slug": "recursion"}], "hasSolution": true, "hasVideoSolution": false, "totalAcceptedRaw": 1311266, "totalSubmissionRaw": 4338691}, "11": {"acRate": 59.273925992661894, "difficulty": "Medium", "likes": 33462, "dislikes": 2150, "categoryTitle": "Algorithms", "frontendQuestionId": "11", "paidOnly": false, "title": "Container With Most Water", "titleSlug": "container-with-most-water", "topicTags": [{"name": "Array", "id": "VG9waWNUYWdOb2RlOjU=", "slug": "array"}, {"name": "Two Pointers", "id": "VG9waWNUYWdOb2RlOjk=", "slug": "two-pointers"}, {"name": "Greedy", "id": "VG9waWNUYWdOb2RlOjE3", "slug": "greedy"}], "hasSolution": true, "hasVideoSolution": true, "totalAcceptedRaw": 4946213, "totalSubmissionRaw": 8344667}, "12": {"acRate": 70.16541247000802, "difficulty": "Medium", "likes": 8383, "dislikes": 5709, "categoryTitle": "Algorithms", "frontendQuestionId": "12", "paidOnly": false, "title": "Integer to Roman", "titleSlug": "integer-to-roman", "topicTags": [{"name": "Hash Table", "id": "VG9waWNUYWdOb2RlOjY=", "slug": "hash-table"}, {"name": "Math", "id": "VG9waWNUYWdOb2RlOjg=", "slug": "math"}, {"name": "String", "id": "VG9waWNUYWdOb2RlOjEw", "slug": "string"}], "hasSolution": true, "hasVideoSolution": true, "totalAcceptedRaw": 2003464, "totalSubmissionRaw": 2855345}, "13": {"acRate": 66.03718342674475, "difficulty": "Easy", "likes": 17259, "dislikes": 1197, "categoryTitle": "Algorithms", "frontendQuestionId": "13", "paidOnly": false, "title": "Roman to Integer", "titleSlug": "roman-to-integer", "topicTags": [{"name": "Hash Table", "id": "VG9waWNUYWdOb2RlOjY=", "slug": "hash-table"}, {"name": "Math", "id": "VG9waWNUYWdOb2RlOjg=", "slug": "math"}, {"name": "String", "id": "VG9waWNUYWdOb2RlOjEw", "slug": "string"}], "hasSolution": true, "hasVideoSolution": true, "totalAcceptedRaw": 5546258, "totalSubmissionRaw": 8398689}, "14": {"acRate": 46.83609394417461, "difficulty": "Easy", "likes": 20777, "dislikes": 4878, "categoryTitle": "Algorithms", "frontendQuestionId": "14", "paidOnly": false, "title": "Longest Common Prefix", "titleSlug": "longest-common-prefix", "topicTags": [{"name": "Array", "id": "VG9waWNUYWdOb2RlOjU=", "slug": "array"}, {"name": "String", "id": "VG9waWNUYWdOb2RlOjEw", "slug": "string"}, {"name": "Trie", "id": "VG9waWNUYWdOb2RlOjI3", "slug": "trie"}], "hasSolution": true, "hasVideoSolution": true, "totalAcceptedRaw": 5370225, "totalSubmissionRaw": 11465998}, "15": {"acRate": 38.32794777797719, "difficulty": "Medium", "likes": 34852, "dislikes": 3236, "categoryTitle": "Algorithms", "frontendQuestionId": "15", "paidOnly": false, "title": "3Sum", "titleSlug": "3sum", "topicTags": [{"name": "Array", "id": "VG9waWNUYWdOb2RlOjU=", "slug": "array"}, {"name": "Two Pointers", "id": "VG9waWNUYWdOb2RlOjk=", "slug": "two-pointers"}, {"name": "Sorting", "id": "VG9waWNUYWdOb2RlOjYxMDQ5", "slug": "sorting"}], "hasSolution": true, "hasVideoSolution": true, "totalAcceptedRaw": 5535440, "totalSubmissionRaw": 14442306}, "16": {"acRate": 47.81922624132322, "difficulty": "Medium", "likes": 11460, "dislikes": 615, "categoryTitle": "Algorithms", "frontendQuestionId": "16", "paidOnly": false, "title": "3Sum Closest", "titleSlug": "3sum-closest", "topicTags": [{"name": "Array", "id": "VG9waWNUYWdOb2RlOjU=", "slug": "array"}, {"name": "Two Pointers", "id": "VG9waWNUYWdOb2RlOjk=", "slug": "two-pointers"}, {"name": "Sorting", "id": "VG9waWNUYWdOb2RlOjYxMDQ5", "slug": "sorting"}], "hasSolution": true, "hasVideoSolution": true, "totalAcceptedRaw": 1711288, "totalSubmissionRaw": 3578661}, "17": {"acRate": 65.23133822710622, "difficulty": "Medium", "likes": 20635, "dislikes": 1118, "categoryTitle": "Algorithms", "frontendQuestionId": "17", "paidOnly": false, "title": "Letter Combinations of a Phone Number", "titleSlug": "letter-combinations-of-a-phone-number", "topicTags": [{"name": "Hash Table", "id": "VG9waWNUYWdOb2RlOjY=", "slug": "hash-table"}, {"name": "String", "id": "VG9waWNUYWdOb2RlOjEw", "slug": "string"}, {"name": "Backtracking", "id": "VG9waWNUYWdOb2RlOjE0", "slug": "backtracking"}], "hasSolution": true, "hasVideoSolution": false, "totalAcceptedRaw": 2862190, "totalSubmissionRaw": 4387753}, "18": {"acRate": 39.68913102036212, "difficulty": "Medium", "likes": 12663, "dislikes": 1525, "categoryTitle": "Algorithms", "frontendQuestionId": "18", "paidOnly": false, "title": "4Sum", "titleSlug": "4sum", "topicTags": [{"name": "Array", "id": "VG9waWNUYWdOb2RlOjU=", "slug": "array"}, {"name": "Two Pointers", "id": "VG9waWNUYWdOb2RlOjk=", "slug": "two-pointers"}, {"name": "Sorting", "id": "VG9waWNUYWdOb2RlOjYxMDQ5", "slug": "sorting"}], "hasSolution": true, "hasVideoSolution": false, "totalAcceptedRaw": 1551515, "totalSubmissionRaw": 3909168}, "19": {"acRate": 50.68578809904803, "difficulty": "Medium", "likes": 20943, "dislikes": 886, "categoryTitle": "Algorithms", "frontendQuestionId": "19", "paidOnly": false, "title": "Remove Nth Node From End of List", "titleSlug": "remove-nth-node-from-end-of-list", "topicTags": [{"name": "Linked List", "id": "VG9waWNUYWdOb2RlOjc=", "slug": "linked-list"}, {"name": "Two Pointers", "id": "VG9waWNUYWdOb2RlOjk=", "slug": "two-pointers"}], "hasSolution": true, "hasVideoSolution": true, "totalAcceptedRaw": 3970152, "totalSubmissionRaw": 7832873}, "20": {"acRate": 43.4756573466021, "difficulty": "Easy", "likes": 27301, "dislikes": 1976, "categoryTitle": "Algorithms", "frontendQuestionId": "20", "paidOnly": false, "title": "Valid Parentheses", "titleSlug": "valid-parentheses", "topicTags": [{"name": "String", "id": "VG9waWNUYWdOb2RlOjEw", "slug": "string"}, {"name": "Stack", "id": "VG9waWNUYWdOb2RlOjE1", "slug": "stack"}], "hasSolution": true, "hasVideoSolution": true, "totalAcceptedRaw": 7064296, "totalSubmissionRaw": 16248858}, "21": {"acRate": 67.74712091225763, "difficulty": "Easy", "likes": 24548, "dislikes": 2411, "categoryTitle": "Algorithms", "frontendQuestionId": "21", "paidOnly": false, "title": "Merge Two Sorted Lists", "titleSlug": "merge-two-sorted-lists", "topicTags": [{"name": "Linked List", "id": "VG9waWNUYWdOb2RlOjc=", "slug": "linked-list"}, {"name": "Recursion", "id": "VG9waWNUYWdOb2RlOjMx", "slug": "recursion"}], "hasSolution": true, "hasVideoSolution": true, "totalAcceptedRaw": 5928519, "totalSubmissionRaw": 8750952}, "22": {"acRate": 78.09111826967326, "difficulty": "Medium", "likes": 22999, "dislikes": 1067, "categoryTitle": "Algorithms", "frontendQuestionId": "22", "paidOnly": false, "title": "Generate Parentheses", "titleSlug": "generate-parentheses", "topicTags": [{"name": "String", "id": "VG9waWNUYWdOb2RlOjEw", "slug": "string"}, {"name": "Dynamic Programming", "id": "VG9waWNUYWdOb2RlOjEz", "slug": "dynamic-programming"}, {"name": "Backtracking", "id": "VG9waWNUYWdOb2RlOjE0", "slug": "backtracking"}], "hasSolution": true, "hasVideoSolution": true, "totalAcceptedRaw": 2715072, "totalSubmissionRaw": 3476800}, "23": {"acRate": 58.549253961650095, "difficulty": "Hard", "likes": 21057, "dislikes": 783, "categoryTitle": "Algorithms", "frontendQuestionId": "23", "paidOnly": false, "title": "Merge k Sorted Lists", "titleSlug": "merge-k-sorted-lists", "topicTags": [{"name": "Linked List", "id": "VG9waWNUYWdOb2RlOjc=", "slug": "linked-list"}, {"name": "Divide and Conquer", "id": "VG9waWNUYWdOb2RlOjEy", "slug": "divide-and-conquer"}, {"name": "Heap (Priority Queue)", "id": "VG9waWNUYWdOb2RlOjYxMDUw", "slug": "heap-priority-queue"}, {"name": "Merge Sort", "id": "VG9waWNUYWdOb2RlOjYxMDUx", "slug": "merge-sort"}], "hasSolution": true, "hasVideoSolution": true, "totalAcceptedRaw": 2823014, "totalSubmissionRaw": 4821604}, "24": {"acRate": 68.67229358848877, "difficulty": "Medium", "likes": 12973, "dislikes": 504, "categoryTitle": "Algorithms", "frontendQuestionId": "24", "paidOnly": false, "title": "Swap Nodes in Pairs", "titleSlug": "swap-nodes-in-pairs", "topicTags": [{"name": "Linked List", "id": "VG9waWNUYWdOb2RlOjc=", "slug": "linked-list"}, {"name": "Recursion", "id": "VG9waWNUYWdOb2RlOjMx", "slug": "recursion"}], "hasSolution": true, "hasVideoSolution": false, "totalAcceptedRaw": 1822825, "totalSubmissionRaw": 2654382}, "25": {"acRate": 64.98137099675816, "difficulty": "Hard", "likes": 15414, "dislikes": 795, "categoryTitle": "Algorithms", "frontendQuestionId": "25", "paidOnly": false, "title": "Reverse Nodes in k-Group", "titleSlug": "reverse-nodes-in-k-group", "topicTags": [{"name": "Linked List", "id": "VG9waWNUYWdOb2RlOjc=", "slug": "linked-list"}, {"name": "Recursion", "id": "VG9waWNUYWdOb2RlOjMx", "slug": "recursion"}], "hasSolution": true, "hasVideoSolution": false, "totalAcceptedRaw": 1433990, "totalSubmissionRaw": 2206771}, "26": {"acRate": 61.94573569058899, "difficulty": "Easy", "likes": 18424, "dislikes": 20378, "categoryTitle": "Algorithms", "frontendQuestionId": "26", "paidOnly": false, "title": "Remove Duplicates from Sorted Array", "titleSlug": "remove-duplicates-from-sorted-array", "topicTags": [{"name": "Array", "id": "VG9waWNUYWdOb2RlOjU=", "slug": "array"}, {"name": "Two Pointers", "id": "VG9waWNUYWdOb2RlOjk=", "slug": "two-pointers"}], "hasSolution": true, "hasVideoSolution": true, "totalAcceptedRaw": 7317438, "totalSubmissionRaw": 11812660}, "27": {"acRate": 61.13127942321665, "difficulty": "Easy", "likes": 4784, "dislikes": 5226, "categoryTitle": "Algorithms", "frontendQuestionId": "27", "paidOnly": false, "title": "Remove Element", "titleSlug": "remove-element", "topicTags": [{"name": "Array", "id": "VG9waWNUYWdOb2RlOjU=", "slug": "array"}, {"name": "Two Pointers", "id": "VG9waWNUYWdOb2RlOjk=", "slug": "two-pointers"}], "hasSolution": true, "hasVideoSolution": true, "totalAcceptedRaw": 4897664, "totalSubmissionRaw": 8011719}, "28": {"acRate": 46.060882166732064, "difficulty": "Easy", "likes": 7382, "dislikes": 560, "categoryTitle": "Algorithms", "frontendQuestionId": "28", "paidOnly": false, "title": "Find the Index of the First Occurrence in a String", "titleSlug": "find-the-index-of-the-first-occurrence-in-a-string", "topicTags": [{"name": "Two Pointers", "id": "VG9waWNUYWdOb2RlOjk=", "slug": "two-pointers"}, {"name": "String", "id": "VG9waWNUYWdOb2RlOjEw", "slug": "string"}, {"name": "String Matching", "id": "VG9waWNUYWdOb2RlOjYxMDUy", "slug": "string-matching"}], "hasSolution": true, "hasVideoSolution": true, "totalAcceptedRaw": 3826818, "totalSubmissionRaw": 8308173}, "29": {"acRate": 19.222431922541226, "difficulty": "Medium", "likes": 5993, "dislikes": 15246, "categoryTitle": "Algorithms", "frontendQuestionId": "29", "paidOnly": false, "title": "Divide Two Integers", "titleSlug": "divide-two-integers", "topicTags": [{"name": "Math", "id": "VG9waWNUYWdOb2RlOjg=", "slug": "math"}, {"name": "Bit Manipulation", "id": "VG9waWNUYWdOb2RlOjE5", "slug": "bit-manipulation"}], "hasSolution": true, "hasVideoSolution": false, "totalAcceptedRaw": 1090009, "totalSubmissionRaw": 5670512}, "30": {"acRate": 33.77779647375794, "difficulty": "Hard", "likes": 2543, "dislikes": 416, "categoryTitle": "Algorithms", "frontendQuestionId": "30", "paidOnly": false, "title": "Substring with Concatenation of All Words", "titleSlug": "substring-with-concatenation-of-all-words", "topicTags": [{"name": "Hash Table", "id": "VG9waWNUYWdOb2RlOjY=", "slug": "hash-table"}, {"name": "String", "id": "VG9waWNUYWdOb2RlOjEw", "slug": "string"}, {"name": "Sliding Window", "id": "VG9waWNUYWdOb2RlOjU1ODIx", "slug": "sliding-window"}], "hasSolution": true, "hasVideoSolution": true, "totalAcceptedRaw": 666464, "totalSubmissionRaw": 1973080}, "31": {"acRate": 44.48547536692198, "difficulty": "Medium", "likes": 21010, "dislikes": 5079, "categoryTitle": "Algorithms", "frontendQuestionId": "31", "paidOnly": false, "title": "Next Permutation", "titleSlug": "next-permutation", "topicTags": [{"name": "Array", "id": "VG9waWNUYWdOb2RlOjU=", "slug": "array"}, {"name": "Two Pointers", "id": "VG9waWNUYWdOb2RlOjk=", "slug": "two-pointers"}], "hasSolution": true, "hasVideoSolution": true, "totalAcceptedRaw": 2128634, "totalSubmissionRaw": 4785009}, "32": {"acRate": 37.74216783725342, "difficulty": "Hard", "likes": 13177, "dislikes": 460, "categoryTitle": "Algorithms", "frontendQuestionId": "32", "paidOnly": false, "title": "Longest Valid Parentheses", "titleSlug": "longest-valid-parentheses", "topicTags": [{"name": "String", "id": "VG9waWNUYWdOb2RlOjEw", "slug": "string"}, {"name": "Dynamic Programming", "id": "VG9waWNUYWdOb2RlOjEz", "slug": "dynamic-programming"}, {"name": "Stack", "id": "VG9waWNUYWdOb2RlOjE1", "slug": "stack"}], "hasSolution": true, "hasVideoSolution": false, "totalAcceptedRaw": 1032768, "totalSubmissionRaw": 2736377}, "33": {"acRate": 43.904859035365185, "difficulty": "Medium", "likes": 29459, "dislikes": 1784, "categoryTitle": "Algorithms", "frontendQuestionId": "33", "paidOnly": false, "title": "Search in Rotated Sorted Array", "titleSlug": "search-in-rotated-sorted-array", "topicTags": [{"name": "Array", "id": "VG9waWNUYWdOb2RlOjU=", "slug": "array"}, {"name": "Binary Search", "id": "VG9waWNUYWdOb2RlOjEx", "slug": "binary-search"}], "hasSolution": true, "hasVideoSolution": false, "totalAcceptedRaw": 4157691, "totalSubmissionRaw": 9469789}, "34": {"acRate": 48.08964190666913, "difficulty": "Medium", "likes": 22897, "dislikes": 623, "categoryTitle": "Algorithms", "frontendQuestionId": "34", "paidOnly": false, "title": "Find First and Last Position of Element in Sorted Array", "titleSlug": "find-first-and-last-position-of-element-in-sorted-array", "topicTags": [{"name": "Array", "id": "VG9waWNUYWdOb2RlOjU=", "slug": "array"}, {"name": "Binary Search", "id": "VG9waWNUYWdOb2RlOjEx", "slug": "binary-search"}], "hasSolution": true, "hasVideoSolution": false, "totalAcceptedRaw": 3102584, "totalSubmissionRaw": 6451668}, "35": {"acRate": 50.401895418854934, "difficulty": "Easy", "likes": 18436, "dislikes": 876, "categoryTitle": "Algorithms", "frontendQuestionId": "35", "paidOnly": false, "title": "Search Insert Position", "titleSlug": "search-insert-position", "topicTags": [{"name": "Array", "id": "VG9waWNUYWdOb2RlOjU=", "slug": "array"}, {"name": "Binary Search", "id": "VG9waWNUYWdOb2RlOjEx", "slug": "binary-search"}], "hasSolution": true, "hasVideoSolution": true, "totalAcceptedRaw": 4433310, "totalSubmissionRaw": 8795910}, "36": {"acRate": 63.977312639602516, "difficulty": "Medium", "likes": 12306, "dislikes": 1253, "categoryTitle": "Algorithms", "frontendQuestionId": "36", "paidOnly": false, "title": "Valid Sudoku", "titleSlug": "valid-sudoku", "topicTags": [{"name": "Array", "id": "VG9waWNUYWdOb2RlOjU=", "slug": "array"}, {"name": "Hash Table", "id": "VG9waWNUYWdOb2RlOjY=", "slug": "hash-table"}, {"name": "Matrix", "id": "VG9waWNUYWdOb2RlOjYxMDUz", "slug": "matrix"}], "hasSolution": true, "hasVideoSolution": false, "totalAcceptedRaw": 2366169, "totalSubmissionRaw": 3698453}, "37": {"acRate": 65.36738808294051, "difficulty": "Hard", "likes": 10935, "dislikes": 337, "categoryTitle": "Algorithms", "frontendQuestionId": "37", "paidOnly": false, "title": "Sudoku Solver", "titleSlug": "sudoku-solver", "topicTags": [{"name": "Array", "id": "VG9waWNUYWdOb2RlOjU=", "slug": "array"}, {"name": "Hash Table", "id": "VG9waWNUYWdOb2RlOjY=", "slug": "hash-table"}, {"name": "Backtracking", "id": "VG9waWNUYWdOb2RlOjE0", "slug": "backtracking"}, {"name": "Matrix", "id": "VG9waWNUYWdOb2RlOjYxMDUz", "slug": "matrix"}], "hasSolution": true, "hasVideoSolution": false, "totalAcceptedRaw": 973995, "totalSubmissionRaw": 1490032}, "38": {"acRate": 62.05448840625881, "difficulty": "Medium", "likes": 5024, "dislikes": 9016, "categoryTitle": "Algorithms", "frontendQuestionId": "38", "paidOnly": false, "title": "Count and Say", "titleSlug": "count-and-say", "topicTags": [{"name": "String", "id": "VG9waWNUYWdOb2RlOjEw", "slug": "string"}], "hasSolution": true, "hasVideoSolution": false, "totalAcceptedRaw": 1353759, "totalSubmissionRaw": 2181565}, "39": {"acRate": 75.8724472124983, "difficulty": "Medium", "likes": 20695, "dislikes": 525, "categoryTitle": "Algorithms", "frontendQuestionId": "39", "paidOnly": false, "title": "Combination Sum", "titleSlug": "combination-sum", "topicTags": [{"name": "Array", "id": "VG9waWNUYWdOb2RlOjU=", "slug": "array"}, {"name": "Backtracking", "id": "VG9waWNUYWdOb2RlOjE0", "slug": "backtracking"}], "hasSolution": true, "hasVideoSolution": true, "totalAcceptedRaw": 2944202, "totalSubmissionRaw": 3880463}, "40": {"acRate": 58.75998957752704, "difficulty": "Medium", "likes": 12074, "dislikes": 377, "categoryTitle": "Algorithms", "frontendQuestionId": "40", "paidOnly": false, "title": "Combination Sum II", "titleSlug": "combination-sum-ii", "topicTags": [{"name": "Array", "id": "VG9waWNUYWdOb2RlOjU=", "slug": "array"}, {"name": "Backtracking", "id": "VG9waWNUYWdOb2RlOjE0", "slug": "backtracking"}], "hasSolution": true, "hasVideoSolution": false, "totalAcceptedRaw": 1603394, "totalSubmissionRaw": 2728716}, "41": {"acRate": 42.203229860436245, "difficulty": "Hard", "likes": 18156, "dislikes": 1972, "categoryTitle": "Algorithms", "frontendQuestionId": "41", "paidOnly": false, "title": "First Missing Positive", "titleSlug": "first-missing-positive", "topicTags": [{"name": "Array", "id": "VG9waWNUYWdOb2RlOjU=", "slug": "array"}, {"name": "Hash Table", "id": "VG9waWNUYWdOb2RlOjY=", "slug": "hash-table"}], "hasSolution": true, "hasVideoSolution": false, "totalAcceptedRaw": 1658932, "totalSubmissionRaw": 3930818}, "42": {"acRate": 66.51939481731853, "difficulty": "Hard", "likes": 35778, "dislikes": 672, "categoryTitle": "Algorithms", "frontendQuestionId": "42", "paidOnly": false, "title": "Trapping Rain Water", "titleSlug": "trapping-rain-water", "topicTags": [{"name": "Array", "id": "VG9waWNUYWdOb2RlOjU=", "slug": "array"}, {"name": "Two Pointers", "id": "VG9waWNUYWdOb2RlOjk=", "slug": "two-pointers"}, {"name": "Dynamic Programming", "id": "VG9waWNUYWdOb2RlOjEz", "slug": "dynamic-programming"}, {"name": "Stack", "id": "VG9waWNUYWdOb2RlOjE1", "slug": "stack"}, {"name": "Monotonic Stack", "id": "VG9waWNUYWdOb2RlOjYxMDU0", "slug": "monotonic-stack"}], "hasSolution": true, "hasVideoSolution": false, "totalAcceptedRaw": 3306263, "totalSubmissionRaw": 4970379}, "43": {"acRate": 43.37354774701334, "difficulty": "Medium", "likes": 7651, "dislikes": 3655, "categoryTitle": "Algorithms", "frontendQuestionId": "43", "paidOnly": false, "title": "Multiply Strings", "titleSlug": "multiply-strings", "topicTags": [{"name": "Math", "id": "VG9waWNUYWdOb2RlOjg=", "slug": "math"}, {"name": "String", "id": "VG9waWNUYWdOb2RlOjEw", "slug": "string"}, {"name": "Simulation", "id": "VG9waWNUYWdOb2RlOjYxMDU1", "slug": "simulation"}], "hasSolution": true, "hasVideoSolution": false, "totalAcceptedRaw": 1098186, "totalSubmissionRaw": 2531925}, "44": {"acRate": 31.15193192035578, "difficulty": "Hard", "likes": 9034, "dislikes": 410, "categoryTitle": "Algorithms", "frontendQuestionId": "44", "paidOnly": false, "title": "Wildcard Matching", "titleSlug": "wildcard-matching", "topicTags": [{"name": "String", "id": "VG9waWNUYWdOb2RlOjEw", "slug": "string"}, {"name": "Dynamic Programming", "id": "VG9waWNUYWdOb2RlOjEz", "slug": "dynamic-programming"}, {"name": "Greedy", "id": "VG9waWNUYWdOb2RlOjE3", "slug": "greedy"}, {"name": "Recursion", "id": "VG9waWNUYWdOb2RlOjMx", "slug": "recursion"}], "hasSolution": true, "hasVideoSolution": false, "totalAcceptedRaw": 823206, "totalSubmissionRaw": 2642544}, "45": {"acRate": 42.31889980221211, "difficulty": "Medium", "likes": 16261, "dislikes": 696, "categoryTitle": "Algorithms", "frontendQuestionId": "45", "paidOnly": false, "title": "Jump Game II", "titleSlug": "jump-game-ii", "topicTags": [{"name": "Array", "id": "VG9waWNUYWdOb2RlOjU=", "slug": "array"}, {"name": "Dynamic Programming", "id": "VG9waWNUYWdOb2RlOjEz", "slug": "dynamic-programming"}, {"name": "Greedy", "id": "VG9waWNUYWdOb2RlOjE3", "slug": "greedy"}], "hasSolution": true, "hasVideoSolution": false, "totalAcceptedRaw": 2009090, "totalSubmissionRaw": 4747501}, "46": {"acRate": 81.48840054310665, "difficulty": "Medium", "likes": 20635, "dislikes": 379, "categoryTitle": "Algorithms", "frontendQuestionId": "46", "paidOnly": false, "title": "Permutations", "titleSlug": "permutations", "topicTags": [{"name": "Array", "id": "VG9waWNUYWdOb2RlOjU=", "slug": "array"}, {"name": "Backtracking", "id": "VG9waWNUYWdOb2RlOjE0", "slug": "backtracking"}], "hasSolution": true, "hasVideoSolution": false, "totalAcceptedRaw": 2928196, "totalSubmissionRaw": 3593389}, "47": {"acRate": 62.7658993201781, "difficulty": "Medium", "likes": 9057, "dislikes": 161, "categoryTitle": "Algorithms", "frontendQuestionId": "47", "paidOnly": false, "title": "Permutations II", "titleSlug": "permutations-ii", "topicTags": [{"name": "Array", "id": "VG9waWNUYWdOb2RlOjU=", "slug": "array"}, {"name": "Backtracking", "id": "VG9waWNUYWdOb2RlOjE0", "slug": "backtracking"}, {"name": "Sorting", "id": "VG9waWNUYWdOb2RlOjYxMDQ5", "slug": "sorting"}], "hasSolution": true, "hasVideoSolution": false, "totalAcceptedRaw": 1229149, "totalSubmissionRaw": 1958307}, "48": {"acRate": 79.13028452256815, "difficulty": "Medium", "likes": 19594, "dislikes": 946, "categoryTitle": "Algorithms", "frontendQuestionId": "48", "paidOnly": false, "title": "Rotate Image", "titleSlug": "rotate-image", "topicTags": [{"name": "Array", "id": "VG9waWNUYWdOb2RlOjU=", "slug": "array"}, {"name": "Math", "id": "VG9waWNUYWdOb2RlOjg=", "slug": "math"}, {"name": "Matrix", "id": "VG9waWNUYWdOb2RlOjYxMDUz", "slug": "matrix"}], "hasSolution": true, "hasVideoSolution": false, "totalAcceptedRaw": 2656008, "totalSubmissionRaw": 3356500}, "49": {"acRate": 71.9768121883233, "difficulty": "Medium", "likes": 21670, "dislikes": 742, "categoryTitle": "Algorithms", "frontendQuestionId": "49", "paidOnly": false, "title": "Group Anagrams", "titleSlug": "group-anagrams", "topicTags": [{"name": "Array", "id": "VG9waWNUYWdOb2RlOjU=", "slug": "array"}, {"name": "Hash Table", "id": "VG9waWNUYWdOb2RlOjY=", "slug": "hash-table"}, {"name": "String", "id": "VG9waWNUYWdOb2RlOjEw", "slug": "string"}, {"name": "Sorting", "id": "VG9waWNUYWdOb2RlOjYxMDQ5", "slug": "sorting"}], "hasSolution": true, "hasVideoSolution": true, "totalAcceptedRaw": 4424539, "totalSubmissionRaw": 6147174}, "50": {"acRate": 38.06668637452007, "difficulty": "Medium", "likes": 11432, "dislikes": 10483, "categoryTitle": "Algorithms", "frontendQuestionId": "50", "paidOnly": false, "title": "Pow(x, n)", "titleSlug": "powx-n", "topicTags": [{"name": "Math", "id": "VG9waWNUYWdOb2RlOjg=", "slug": "math"}, {"name": "Recursion", "id": "VG9waWNUYWdOb2RlOjMx", "slug": "recursion"}], "hasSolution": true, "hasVideoSolution": false, "totalAcceptedRaw": 2557368, "totalSubmissionRaw": 6718129}, "51": {"acRate": 74.67412441205077, "difficulty": "Hard", "likes": 14053, "dislikes": 341, "categoryTitle": "Algorithms", "frontendQuestionId": "51", "paidOnly": false, "title": "N-Queens", "titleSlug": "n-queens", "topicTags": [{"name": "Array", "id": "VG9waWNUYWdOb2RlOjU=", "slug": "array"}, {"name": "Backtracking", "id": "VG9waWNUYWdOb2RlOjE0", "slug": "backtracking"}], "hasSolution": true, "hasVideoSolution": false, "totalAcceptedRaw": 1180053, "totalSubmissionRaw": 1580272}, "52": {"acRate": 77.95207308619608, "difficulty": "Hard", "likes": 4228, "dislikes": 282, "categoryTitle": "Algorithms", "frontendQuestionId": "52", "paidOnly": false, "title": "N-Queens II", "titleSlug": "n-queens-ii", "topicTags": [{"name": "Backtracking", "id": "VG9waWNUYWdOb2RlOjE0", "slug": "backtracking"}], "hasSolution": true, "hasVideoSolution": false, "totalAcceptedRaw": 564513, "totalSubmissionRaw": 724181}, "53": {"acRate": 52.82223911110799, "difficulty": "Medium", "likes": 37262, "dislikes": 1580, "categoryTitle": "Algorithms", "frontendQuestionId": "53", "paidOnly": false, "title": "Maximum Subarray", "titleSlug": "maximum-subarray", "topicTags": [{"name": "Array", "id": "VG9waWNUYWdOb2RlOjU=", "slug": "array"}, {"name": "Divide and Conquer", "id": "VG9waWNUYWdOb2RlOjEy", "slug": "divide-and-conquer"}, {"name": "Dynamic Programming", "id": "VG9waWNUYWdOb2RlOjEz", "slug": "dynamic-programming"}], "hasSolution": true, "hasVideoSolution": true, "totalAcceptedRaw": 5731199, "totalSubmissionRaw": 10849981}, "54": {"acRate": 55.81292554783642, "difficulty": "Medium", "likes": 17087, "dislikes": 1535, "categoryTitle": "Algorithms", "frontendQuestionId": "54", "paidOnly": false, "title": "Spiral Matrix", "titleSlug": "spiral-matrix", "topicTags": [{"name": "Array", "id": "VG9waWNUYWdOb2RlOjU=", "slug": "array"}, {"name": "Matrix", "id": "VG9waWNUYWdOb2RlOjYxMDUz", "slug": "matrix"}, {"name": "Simulation", "id": "VG9waWNUYWdOb2RlOjYxMDU1", "slug": "simulation"}], "hasSolution": true, "hasVideoSolution": false, "totalAcceptedRaw": 2241283, "totalSubmissionRaw": 4015706}, "55": {"acRate": 40.32169206946297, "difficulty": "Medium", "likes": 21452, "dislikes": 1470, "categoryTitle": "Algorithms", "frontendQuestionId": "55", "paidOnly": false, "title": "Jump Game", "titleSlug": "jump-game", "topicTags": [{"name": "Array", "id": "VG9waWNUYWdOb2RlOjU=", "slug": "array"}, {"name": "Dynamic Programming", "id": "VG9waWNUYWdOb2RlOjEz", "slug": "dynamic-programming"}, {"name": "Greedy", "id": "VG9waWNUYWdOb2RlOjE3", "slug": "greedy"}], "hasSolution": true, "hasVideoSolution": false, "totalAcceptedRaw": 3008847, "totalSubmissionRaw": 7462106}, "56": {"acRate": 50.86960424904638, "difficulty": "Medium", "likes": 24298, "dislikes": 893, "categoryTitle": "Algorithms", "frontendQuestionId": "56", "paidOnly": false, "title": "Merge Intervals", "titleSlug": "merge-intervals", "topicTags": [{"name": "Array", "id": "VG9waWNUYWdOb2RlOjU=", "slug": "array"}, {"name": "Sorting", "id": "VG9waWNUYWdOb2RlOjYxMDQ5", "slug": "sorting"}], "hasSolution": true, "hasVideoSolution": true, "totalAcceptedRaw": 3734193, "totalSubmissionRaw": 7340731}, "57": {"acRate": 44.562702600819186, "difficulty": "Medium", "likes": 11660, "dislikes": 908, "categoryTitle": "Algorithms", "frontendQuestionId": "57", "paidOnly": false, "title": "Insert Interval", "titleSlug": "insert-interval", "topicTags": [{"name": "Array", "id": "VG9waWNUYWdOb2RlOjU=", "slug": "array"}], "hasSolution": true, "hasVideoSolution": false, "totalAcceptedRaw": 1669164, "totalSubmissionRaw": 3745659}, "58": {"acRate": 57.98251586954451, "difficulty": "Easy", "likes": 6245, "dislikes": 350, "categoryTitle": "Algorithms", "frontendQuestionId": "58", "paidOnly": false, "title": "Length of Last Word", "titleSlug": "length-of-last-word", "topicTags": [{"name": "String", "id": "VG9waWNUYWdOb2RlOjEw", "slug": "string"}], "hasSolution": true, "hasVideoSolution": false, "totalAcceptedRaw": 3200066, "totalSubmissionRaw": 5519026}, "59": {"acRate": 74.46978729353647, "difficulty": "Medium", "likes": 6848, "dislikes": 283, "categoryTitle": "Algorithms", "frontendQuestionId": "59", "paidOnly": false, "title": "Spiral Matrix II", "titleSlug": "spiral-matrix-ii", "topicTags": [{"name": "Array", "id": "VG9waWNUYWdOb2RlOjU=", "slug": "array"}, {"name": "Matrix", "id": "VG9waWNUYWdOb2RlOjYxMDUz", "slug": "matrix"}, {"name": "Simulation", "id": "VG9waWNUYWdOb2RlOjYxMDU1", "slug": "simulation"}], "hasSolution": true, "hasVideoSolution": false, "totalAcceptedRaw": 767012, "totalSubmissionRaw": 1029964}, "60": {"acRate": 51.790955842759715, "difficulty": "Hard", "likes": 7178, "dislikes": 502, "categoryTitle": "Algorithms", "frontendQuestionId": "60", "paidOnly": false, "title": "Permutation Sequence", "titleSlug": "permutation-sequence", "topicTags": [{"name": "Math", "id": "VG9waWNUYWdOb2RlOjg=", "slug": "math"}, {"name": "Recursion", "id": "VG9waWNUYWdOb2RlOjMx", "slug": "recursion"}], "hasSolution": true, "hasVideoSolution": false, "totalAcceptedRaw": 541505, "totalSubmissionRaw": 1045559}, "61": {"acRate": 40.98355695037534, "difficulty": "Medium", "likes": 11059, "dislikes": 1538, "categoryTitle": "Algorithms", "frontendQuestionId": "61", "paidOnly": false, "title": "Rotate List", "titleSlug": "rotate-list", "topicTags": [{"name": "Linked List", "id": "VG9waWNUYWdOb2RlOjc=", "slug": "linked-list"}, {"name": "Two Pointers", "id": "VG9waWNUYWdOb2RlOjk=", "slug": "two-pointers"}], "hasSolution": true, "hasVideoSolution": false, "totalAcceptedRaw": 1503347, "totalSubmissionRaw": 3668173}, "62": {"acRate": 66.44472617893454, "difficulty": "Medium", "likes": 18160, "dislikes": 491, "categoryTitle": "Algorithms", "frontendQuestionId": "62", "paidOnly": false, "title": "Unique Paths", "titleSlug": "unique-paths", "topicTags": [{"name": "Math", "id": "VG9waWNUYWdOb2RlOjg=", "slug": "math"}, {"name": "Dynamic Programming", "id": "VG9waWNUYWdOb2RlOjEz", "slug": "dynamic-programming"}, {"name": "Combinatorics", "id": "VG9waWNUYWdOb2RlOjYxMDU2", "slug": "combinatorics"}], "hasSolution": true, "hasVideoSolution": false, "totalAcceptedRaw": 2672872, "totalSubmissionRaw": 4022700}, "63": {"acRate": 43.998195838807746, "difficulty": "Medium", "likes": 9585, "dislikes": 555, "categoryTitle": "Algorithms", "frontendQuestionId": "63", "paidOnly": false, "title": "Unique Paths II", "titleSlug": "unique-paths-ii", "topicTags": [{"name": "Array", "id": "VG9waWNUYWdOb2RlOjU=", "slug": "array"}, {"name": "Dynamic Programming", "id": "VG9waWNUYWdOb2RlOjEz", "slug": "dynamic-programming"}, {"name": "Matrix", "id": "VG9waWNUYWdOb2RlOjYxMDUz", "slug": "matrix"}], "hasSolution": true, "hasVideoSolution": false, "totalAcceptedRaw": 1400793, "totalSubmissionRaw": 3183751}, "64": {"acRate": 67.63357051304901, "difficulty": "Medium", "likes": 13530, "dislikes": 196, "categoryTitle": "Algorithms", "frontendQuestionId": "64", "paidOnly": false, "title": "Minimum Path Sum", "titleSlug": "minimum-path-sum", "topicTags": [{"name": "Array", "id": "VG9waWNUYWdOb2RlOjU=", "slug": "array"}, {"name": "Dynamic Programming", "id": "VG9waWNUYWdOb2RlOjEz", "slug": "dynamic-programming"}, {"name": "Matrix", "id": "VG9waWNUYWdOb2RlOjYxMDUz", "slug": "matrix"}], "hasSolution": true, "hasVideoSolution": false, "totalAcceptedRaw": 1745544, "totalSubmissionRaw": 2580884}, "65": {"acRate": 22.445578196043304, "difficulty": "Hard", "likes": 1475, "dislikes": 2200, "categoryTitle": "Algorithms", "frontendQuestionId": "65", "paidOnly": false, "title": "Valid Number", "titleSlug": "valid-number", "topicTags": [{"name": "String", "id": "VG9waWNUYWdOb2RlOjEw", "slug": "string"}], "hasSolution": true, "hasVideoSolution": false, "totalAcceptedRaw": 498152, "totalSubmissionRaw": 2219377}, "66": {"acRate": 49.29842646577578, "difficulty": "Easy", "likes": 11548, "dislikes": 5586, "categoryTitle": "Algorithms", "frontendQuestionId": "66", "paidOnly": false, "title": "Plus One", "titleSlug": "plus-one", "topicTags": [{"name": "Array", "id": "VG9waWNUYWdOb2RlOjU=", "slug": "array"}, {"name": "Math", "id": "VG9waWNUYWdOb2RlOjg=", "slug": "math"}], "hasSolution": true, "hasVideoSolution": false, "totalAcceptedRaw": 3513057, "totalSubmissionRaw": 7126102}, "67": {"acRate": 56.69840174034502, "difficulty": "Easy", "likes": 10359, "dislikes": 1090, "categoryTitle": "Algorithms", "frontendQuestionId": "67", "paidOnly": false, "title": "Add Binary", "titleSlug": "add-binary", "topicTags": [{"name": "Math", "id": "VG9waWNUYWdOb2RlOjg=", "slug": "math"}, {"name": "String", "id": "VG9waWNUYWdOb2RlOjEw", "slug": "string"}, {"name": "Bit Manipulation", "id": "VG9waWNUYWdOb2RlOjE5", "slug": "bit-manipulation"}, {"name": "Simulation", "id": "VG9waWNUYWdOb2RlOjYxMDU1", "slug": "simulation"}], "hasSolution": true, "hasVideoSolution": false, "totalAcceptedRaw": 2118921, "totalSubmissionRaw": 3737182}, "68": {"acRate": 50.12116244532271, "difficulty": "Hard", "likes": 4470, "dislikes": 5316, "categoryTitle": "Algorithms", "frontendQuestionId": "68", "paidOnly": false, "title": "Text Justification", "titleSlug": "text-justification", "topicTags": [{"name": "Array", "id": "VG9waWNUYWdOb2RlOjU=", "slug": "array"}, {"name": "String", "id": "VG9waWNUYWdOb2RlOjEw", "slug": "string"}, {"name": "Simulation", "id": "VG9waWNUYWdOb2RlOjYxMDU1", "slug": "simulation"}], "hasSolution": true, "hasVideoSolution": false, "totalAcceptedRaw": 617608, "totalSubmissionRaw": 1232230}, "69": {"acRate": 41.230565626690115, "difficulty": "Easy", "likes": 9477, "dislikes": 4628, "categoryTitle": "Algorithms", "frontendQuestionId": "69", "paidOnly": false, "title": "Sqrt(x)", "titleSlug": "sqrtx", "topicTags": [{"name": "Math", "id": "VG9waWNUYWdOb2RlOjg=", "slug": "math"}, {"name": "Binary Search", "id": "VG9waWNUYWdOb2RlOjEx", "slug": "binary-search"}], "hasSolution": true, "hasVideoSolution": true, "totalAcceptedRaw": 2984592, "totalSubmissionRaw": 7238788}, "70": {"acRate": 53.84558117224446, "difficulty": "Easy", "likes": 24146, "dislikes": 1022, "categoryTitle": "Algorithms", "frontendQuestionId": "70", "paidOnly": false, "title": "Climbing Stairs", "titleSlug": "climbing-stairs", "topicTags": [{"name": "Math", "id": "VG9waWNUYWdOb2RlOjg=", "slug": "math"}, {"name": "Dynamic Programming", "id": "VG9waWNUYWdOb2RlOjEz", "slug": "dynamic-programming"}, {"name": "Memoization", "id": "VG9waWNUYWdOb2RlOjMz", "slug": "memoization"}], "hasSolution": true, "hasVideoSolution": false, "totalAcceptedRaw": 4831422, "totalSubmissionRaw": 8972738}, "71": {"acRate": 49.73219515945823, "difficulty": "Medium", "likes": 6437, "dislikes": 1396, "categoryTitle": "Algorithms", "frontendQuestionId": "71", "paidOnly": false, "title": "Simplify Path", "titleSlug": "simplify-path", "topicTags": [{"name": "String", "id": "VG9waWNUYWdOb2RlOjEw", "slug": "string"}, {"name": "Stack", "id": "VG9waWNUYWdOb2RlOjE1", "slug": "stack"}], "hasSolution": true, "hasVideoSolution": true, "totalAcceptedRaw": 1254793, "totalSubmissionRaw": 2523103}, "72": {"acRate": 59.96067548641286, "difficulty": "Medium", "likes": 16239, "dislikes": 319, "categoryTitle": "Algorithms", "frontendQuestionId": "72", "paidOnly": false, "title": "Edit Distance", "titleSlug": "edit-distance", "topicTags": [{"name": "String", "id": "VG9waWNUYWdOb2RlOjEw", "slug": "string"}, {"name": "Dynamic Programming", "id": "VG9waWNUYWdOb2RlOjEz", "slug": "dynamic-programming"}], "hasSolution": true, "hasVideoSolution": false, "totalAcceptedRaw": 1360998, "totalSubmissionRaw": 2269803}, "73": {"acRate": 62.18311639755484, "difficulty": "Medium", "likes": 16825, "dislikes": 848, "categoryTitle": "Algorithms", "frontendQuestionId": "73", "paidOnly": false, "title": "Set Matrix Zeroes", "titleSlug": "set-matrix-zeroes", "topicTags": [{"name": "Array", "id": "VG9waWNUYWdOb2RlOjU=", "slug": "array"}, {"name": "Hash Table", "id": "VG9waWNUYWdOb2RlOjY=", "slug": "hash-table"}, {"name": "Matrix", "id": "VG9waWNUYWdOb2RlOjYxMDUz", "slug": "matrix"}], "hasSolution": true, "hasVideoSolution": false, "totalAcceptedRaw": 2424898, "totalSubmissionRaw": 3899611}, "74": {"acRate": 53.33262599427879, "difficulty": "Medium", "likes": 17615, "dislikes": 476, "categoryTitle": "Algorithms", "frontendQuestionId": "74", "paidOnly": false, "title": "Search a 2D Matrix", "titleSlug": "search-a-2d-matrix", "topicTags": [{"name": "Array", "id": "VG9waWNUYWdOb2RlOjU=", "slug": "array"}, {"name": "Binary Search", "id": "VG9waWNUYWdOb2RlOjEx", "slug": "binary-search"}, {"name": "Matrix", "id": "VG9waWNUYWdOb2RlOjYxMDUz", "slug": "matrix"}], "hasSolution": true, "hasVideoSolution": false, "totalAcceptedRaw": 2719381, "totalSubmissionRaw": 5098896}, "75": {"acRate": 68.89603615305343, "difficulty": "Medium", "likes": 21179, "dislikes": 753, "categoryTitle": "Algorithms", "frontendQuestionId": "75", "paidOnly": false, "title": "Sort Colors", "titleSlug": "sort-colors", "topicTags": [{"name": "Array", "id": "VG9waWNUYWdOb2RlOjU=", "slug": "array"}, {"name": "Two Pointers", "id": "VG9waWNUYWdOb2RlOjk=", "slug": "two-pointers"}, {"name": "Sorting", "id": "VG9waWNUYWdOb2RlOjYxMDQ5", "slug": "sorting"}], "hasSolution": true, "hasVideoSolution": false, "totalAcceptedRaw": 3471074, "totalSubmissionRaw": 5038133}, "76": {"acRate": 46.68827739390808, "difficulty": "Hard", "likes": 19821, "dislikes": 838, "categoryTitle": "Algorithms", "frontendQuestionId": "76", "paidOnly": false, "title": "Minimum Window Substring", "titleSlug": "minimum-window-substring", "topicTags": [{"name": "Hash Table", "id": "VG9waWNUYWdOb2RlOjY=", "slug": "hash-table"}, {"name": "String", "id": "VG9waWNUYWdOb2RlOjEw", "slug": "string"}, {"name": "Sliding Window", "id": "VG9waWNUYWdOb2RlOjU1ODIx", "slug": "sliding-window"}], "hasSolution": true, "hasVideoSolution": false, "totalAcceptedRaw": 2019991, "totalSubmissionRaw": 4326551}, "77": {"acRate": 74.0003415136775, "difficulty": "Medium", "likes": 8830, "dislikes": 250, "categoryTitle": "Algorithms", "frontendQuestionId": "77", "paidOnly": false, "title": "Combinations", "titleSlug": "combinations", "topicTags": [{"name": "Backtracking", "id": "VG9waWNUYWdOb2RlOjE0", "slug": "backtracking"}], "hasSolution": true, "hasVideoSolution": false, "totalAcceptedRaw": 1265430, "totalSubmissionRaw": 1710031}, "78": {"acRate": 81.86943347927598, "difficulty": "Medium", "likes": 18963, "dislikes": 334, "categoryTitle": "Algorithms", "frontendQuestionId": "78", "paidOnly": false, "title": "Subsets", "titleSlug": "subsets", "topicTags": [{"name": "Array", "id": "VG9waWNUYWdOb2RlOjU=", "slug": "array"}, {"name": "Backtracking", "id": "VG9waWNUYWdOb2RlOjE0", "slug": "backtracking"}, {"name": "Bit Manipulation", "id": "VG9waWNUYWdOb2RlOjE5", "slug": "bit-manipulation"}], "hasSolution": true, "hasVideoSolution": true, "totalAcceptedRaw": 2873274, "totalSubmissionRaw": 3509584}, "79": {"acRate": 46.607150223849665, "difficulty": "Medium", "likes": 17434, "dislikes": 746, "categoryTitle": "Algorithms", "frontendQuestionId": "79", "paidOnly": false, "title": "Word Search", "titleSlug": "word-search", "topicTags": [{"name": "Array", "id": "VG9waWNUYWdOb2RlOjU=", "slug": "array"}, {"name": "String", "id": "VG9waWNUYWdOb2RlOjEw", "slug": "string"}, {"name": "Backtracking", "id": "VG9waWNUYWdOb2RlOjE0", "slug": "backtracking"}, {"name": "Depth-First Search", "id": "VG9waWNUYWdOb2RlOjIx", "slug": "depth-first-search"}, {"name": "Matrix", "id": "VG9waWNUYWdOb2RlOjYxMDUz", "slug": "matrix"}], "hasSolution": true, "hasVideoSolution": false, "totalAcceptedRaw": 2372519, "totalSubmissionRaw": 5090464}, "80": {"acRate": 64.07517827005151, "difficulty": "Medium", "likes": 8093, "dislikes": 1506, "categoryTitle": "Algorithms", "frontendQuestionId": "80", "paidOnly": false, "title": "Remove Duplicates from Sorted Array II", "titleSlug": "remove-duplicates-from-sorted-array-ii", "topicTags": [{"name": "Array", "id": "VG9waWNUYWdOb2RlOjU=", "slug": "array"}, {"name": "Two Pointers", "id": "VG9waWNUYWdOb2RlOjk=", "slug": "two-pointers"}], "hasSolution": true, "hasVideoSolution": false, "totalAcceptedRaw": 1812857, "totalSubmissionRaw": 2829263}, "81": {"acRate": 39.57561955499262, "difficulty": "Medium", "likes": 9485, "dislikes": 1114, "categoryTitle": "Algorithms", "frontendQuestionId": "81", "paidOnly": false, "title": "Search in Rotated Sorted Array II", "titleSlug": "search-in-rotated-sorted-array-ii", "topicTags": [{"name": "Array", "id": "VG9waWNUYWdOb2RlOjU=", "slug": "array"}, {"name": "Binary Search", "id": "VG9waWNUYWdOb2RlOjEx", "slug": "binary-search"}], "hasSolution": true, "hasVideoSolution": false, "totalAcceptedRaw": 1152333, "totalSubmissionRaw": 2911725}, "82": {"acRate": 51.10826338106547, "difficulty": "Medium", "likes": 9569, "dislikes": 278, "categoryTitle": "Algorithms", "frontendQuestionId": "82", "paidOnly": false, "title": "Remove Duplicates from Sorted List II", "titleSlug": "remove-duplicates-from-sorted-list-ii", "topicTags": [{"name": "Linked List", "id": "VG9waWNUYWdOb2RlOjc=", "slug": "linked-list"}, {"name": "Two Pointers", "id": "VG9waWNUYWdOb2RlOjk=", "slug": "two-pointers"}], "hasSolution": true, "hasVideoSolution": false, "totalAcceptedRaw": 1043319, "totalSubmissionRaw": 2041391}, "83": {"acRate": 56.04031465834546, "difficulty": "Easy", "likes": 9699, "dislikes": 358, "categoryTitle": "Algorithms", "frontendQuestionId": "83", "paidOnly": false, "title": "Remove Duplicates from Sorted List", "titleSlug": "remove-duplicates-from-sorted-list", "topicTags": [{"name": "Linked List", "id": "VG9waWNUYWdOb2RlOjc=", "slug": "linked-list"}], "hasSolution": true, "hasVideoSolution": true, "totalAcceptedRaw": 2230513, "totalSubmissionRaw": 3980192}, "84": {"acRate": 49.06528227891522, "difficulty": "Hard", "likes": 19261, "dislikes": 373, "categoryTitle": "Algorithms", "frontendQuestionId": "84", "paidOnly": false, "title": "Largest Rectangle in Histogram", "titleSlug": "largest-rectangle-in-histogram", "topicTags": [{"name": "Array", "id": "VG9waWNUYWdOb2RlOjU=", "slug": "array"}, {"name": "Stack", "id": "VG9waWNUYWdOb2RlOjE1", "slug": "stack"}, {"name": "Monotonic Stack", "id": "VG9waWNUYWdOb2RlOjYxMDU0", "slug": "monotonic-stack"}], "hasSolution": true, "hasVideoSolution": true, "totalAcceptedRaw": 1437522, "totalSubmissionRaw": 2929813}, "85": {"acRate": 57.789032881306504, "difficulty": "Hard", "likes": 11945, "dislikes": 224, "categoryTitle": "Algorithms", "frontendQuestionId": "85", "paidOnly": false, "title": "Maximal Rectangle", "titleSlug": "maximal-rectangle", "topicTags": [{"name": "Array", "id": "VG9waWNUYWdOb2RlOjU=", "slug": "array"}, {"name": "Dynamic Programming", "id": "VG9waWNUYWdOb2RlOjEz", "slug": "dynamic-programming"}, {"name": "Stack", "id": "VG9waWNUYWdOb2RlOjE1", "slug": "stack"}, {"name": "Matrix", "id": "VG9waWNUYWdOb2RlOjYxMDUz", "slug": "matrix"}, {"name": "Monotonic Stack", "id": "VG9waWNUYWdOb2RlOjYxMDU0", "slug": "monotonic-stack"}], "hasSolution": true, "hasVideoSolution": false, "totalAcceptedRaw": 760929, "totalSubmissionRaw": 1316736}, "86": {"acRate": 60.36357704589099, "difficulty": "Medium", "likes": 7960, "dislikes": 978, "categoryTitle": "Algorithms", "frontendQuestionId": "86", "paidOnly": false, "title": "Partition List", "titleSlug": "partition-list", "topicTags": [{"name": "Linked List", "id": "VG9waWNUYWdOb2RlOjc=", "slug": "linked-list"}, {"name": "Two Pointers", "id": "VG9waWNUYWdOb2RlOjk=", "slug": "two-pointers"}], "hasSolution": true, "hasVideoSolution": false, "totalAcceptedRaw": 862207, "totalSubmissionRaw": 1428359}, "87": {"acRate": 43.642234946924596, "difficulty": "Hard", "likes": 3600, "dislikes": 1307, "categoryTitle": "Algorithms", "frontendQuestionId": "87", "paidOnly": false, "title": "Scramble String", "titleSlug": "scramble-string", "topicTags": [{"name": "String", "id": "VG9waWNUYWdOb2RlOjEw", "slug": "string"}, {"name": "Dynamic Programming", "id": "VG9waWNUYWdOb2RlOjEz", "slug": "dynamic-programming"}], "hasSolution": true, "hasVideoSolution": false, "totalAcceptedRaw": 299757, "totalSubmissionRaw": 686851}, "88": {"acRate": 54.13228368908981, "difficulty": "Easy", "likes": 18434, "dislikes": 2577, "categoryTitle": "Algorithms", "frontendQuestionId": "88", "paidOnly": false, "title": "Merge Sorted Array", "titleSlug": "merge-sorted-array", "topicTags": [{"name": "Array", "id": "VG9waWNUYWdOb2RlOjU=", "slug": "array"}, {"name": "Two Pointers", "id": "VG9waWNUYWdOb2RlOjk=", "slug": "two-pointers"}, {"name": "Sorting", "id": "VG9waWNUYWdOb2RlOjYxMDQ5", "slug": "sorting"}], "hasSolution": true, "hasVideoSolution": true, "totalAcceptedRaw": 5330760, "totalSubmissionRaw": 9847654}, "89": {"acRate": 63.759550122312106, "difficulty": "Medium", "likes": 2497, "dislikes": 2829, "categoryTitle": "Algorithms", "frontendQuestionId": "89", "paidOnly": false, "title": "Gray Code", "titleSlug": "gray-code", "topicTags": [{"name": "Math", "id": "VG9waWNUYWdOb2RlOjg=", "slug": "math"}, {"name": "Backtracking", "id": "VG9waWNUYWdOb2RlOjE0", "slug": "backtracking"}, {"name": "Bit Manipulation", "id": "VG9waWNUYWdOb2RlOjE5", "slug": "bit-manipulation"}], "hasSolution": true, "hasVideoSolution": false, "totalAcceptedRaw": 397741, "totalSubmissionRaw": 623814}, "90": {"acRate": 60.67583067238155, "difficulty": "Medium", "likes": 10774, "dislikes": 403, "categoryTitle": "Algorithms", "frontendQuestionId": "90", "paidOnly": false, "title": "Subsets II", "titleSlug": "subsets-ii", "topicTags": [{"name": "Array", "id": "VG9waWNUYWdOb2RlOjU=", "slug": "array"}, {"name": "Backtracking", "id": "VG9waWNUYWdOb2RlOjE0", "slug": "backtracking"}, {"name": "Bit Manipulation", "id": "VG9waWNUYWdOb2RlOjE5", "slug": "bit-manipulation"}], "hasSolution": true, "hasVideoSolution": false, "totalAcceptedRaw": 1405571, "totalSubmissionRaw": 2316525}, "91": {"acRate": 37.45984111565524, "difficulty": "Medium", "likes": 12756, "dislikes": 4608, "categoryTitle": "Algorithms", "frontendQuestionId": "91", "paidOnly": false, "title": "Decode Ways", "titleSlug": "decode-ways", "topicTags": [{"name": "String", "id": "VG9waWNUYWdOb2RlOjEw", "slug": "string"}, {"name": "Dynamic Programming", "id": "VG9waWNUYWdOb2RlOjEz", "slug": "dynamic-programming"}], "hasSolution": true, "hasVideoSolution": true, "totalAcceptedRaw": 1595768, "totalSubmissionRaw": 4259949}, "92": {"acRate": 50.77256661456913, "difficulty": "Medium", "likes": 12770, "dislikes": 773, "categoryTitle": "Algorithms", "frontendQuestionId": "92", "paidOnly": false, "title": "Reverse Linked List II", "titleSlug": "reverse-linked-list-ii", "topicTags": [{"name": "Linked List", "id": "VG9waWNUYWdOb2RlOjc=", "slug": "linked-list"}], "hasSolution": true, "hasVideoSolution": true, "totalAcceptedRaw": 1241270, "totalSubmissionRaw": 2444769}, "93": {"acRate": 54.9858066463922, "difficulty": "Medium", "likes": 5595, "dislikes": 818, "categoryTitle": "Algorithms", "frontendQuestionId": "93", "paidOnly": false, "title": "Restore IP Addresses", "titleSlug": "restore-ip-addresses", "topicTags": [{"name": "String", "id": "VG9waWNUYWdOb2RlOjEw", "slug": "string"}, {"name": "Backtracking", "id": "VG9waWNUYWdOb2RlOjE0", "slug": "backtracking"}], "hasSolution": true, "hasVideoSolution": false, "totalAcceptedRaw": 597376, "totalSubmissionRaw": 1086421}, "94": {"acRate": 79.55418470266649, "difficulty": "Easy", "likes": 14714, "dislikes": 882, "categoryTitle": "Algorithms", "frontendQuestionId": "94", "paidOnly": false, "title": "Binary Tree Inorder Traversal", "titleSlug": "binary-tree-inorder-traversal", "topicTags": [{"name": "Stack", "id": "VG9waWNUYWdOb2RlOjE1", "slug": "stack"}, {"name": "Tree", "id": "VG9waWNUYWdOb2RlOjIw", "slug": "tree"}, {"name": "Depth-First Search", "id": "VG9waWNUYWdOb2RlOjIx", "slug": "depth-first-search"}, {"name": "Binary Tree", "id": "VG9waWNUYWdOb2RlOjYxMDU3", "slug": "binary-tree"}], "hasSolution": true, "hasVideoSolution": false, "totalAcceptedRaw": 3515998, "totalSubmissionRaw": 4419626}, "95": {"acRate": 61.68007117595244, "difficulty": "Medium", "likes": 7914, "dislikes": 581, "categoryTitle": "Algorithms", "frontendQuestionId": "95", "paidOnly": false, "title": "Unique Binary Search Trees II", "titleSlug": "unique-binary-search-trees-ii", "topicTags": [{"name": "Dynamic Programming", "id": "VG9waWNUYWdOb2RlOjEz", "slug": "dynamic-programming"}, {"name": "Backtracking", "id": "VG9waWNUYWdOb2RlOjE0", "slug": "backtracking"}, {"name": "Tree", "id": "VG9waWNUYWdOb2RlOjIw", "slug": "tree"}, {"name": "Binary Search Tree", "id": "VG9waWNUYWdOb2RlOjMw", "slug": "binary-search-tree"}, {"name": "Binary Tree", "id": "VG9waWNUYWdOb2RlOjYxMDU3", "slug": "binary-tree"}], "hasSolution": true, "hasVideoSolution": false, "totalAcceptedRaw": 557388, "totalSubmissionRaw": 903676}, "96": {"acRate": 63.16302950160484, "difficulty": "Medium", "likes": 10939, "dislikes": 444, "categoryTitle": "Algorithms", "frontendQuestionId": "96", "paidOnly": false, "title": "Unique Binary Search Trees", "titleSlug": "unique-binary-search-trees", "topicTags": [{"name": "Math", "id": "VG9waWNUYWdOb2RlOjg=", "slug": "math"}, {"name": "Dynamic Programming", "id": "VG9waWNUYWdOb2RlOjEz", "slug": "dynamic-programming"}, {"name": "Tree", "id": "VG9waWNUYWdOb2RlOjIw", "slug": "tree"}, {"name": "Binary Search Tree", "id": "VG9waWNUYWdOb2RlOjMw", "slug": "binary-search-tree"}, {"name": "Binary Tree", "id": "VG9waWNUYWdOb2RlOjYxMDU3", "slug": "binary-tree"}], "hasSolution": true, "hasVideoSolution": false, "totalAcceptedRaw": 830645, "totalSubmissionRaw": 1315081}, "97": {"acRate": 43.30547160683003, "difficulty": "Medium", "likes": 8782, "dislikes": 549, "categoryTitle": "Algorithms", "frontendQuestionId": "97", "paidOnly": false, "title": "Interleaving String", "titleSlug": "interleaving-string", "topicTags": [{"name": "String", "id": "VG9waWNUYWdOb2RlOjEw", "slug": "string"}, {"name": "Dynamic Programming", "id": "VG9waWNUYWdOb2RlOjEz", "slug": "dynamic-programming"}], "hasSolution": true, "hasVideoSolution": false, "totalAcceptedRaw": 743836, "totalSubmissionRaw": 1717649}, "98": {"acRate": 35.19771924462593, "difficulty": "Medium", "likes": 18176, "dislikes": 1441, "categoryTitle": "Algorithms", "frontendQuestionId": "98", "paidOnly": false, "title": "Validate Binary Search Tree", "titleSlug": "validate-binary-search-tree", "topicTags": [{"name": "Tree", "id": "VG9waWNUYWdOb2RlOjIw", "slug": "tree"}, {"name": "Depth-First Search", "id": "VG9waWNUYWdOb2RlOjIx", "slug": "depth-first-search"}, {"name": "Binary Search Tree", "id": "VG9waWNUYWdOb2RlOjMw", "slug": "binary-search-tree"}, {"name": "Binary Tree", "id": "VG9waWNUYWdOb2RlOjYxMDU3", "slug": "binary-tree"}], "hasSolution": true, "hasVideoSolution": true, "totalAcceptedRaw": 3180821, "totalSubmissionRaw": 9037007}, "99": {"acRate": 58.43063818658996, "difficulty": "Medium", "likes": 8519, "dislikes": 287, "categoryTitle": "Algorithms", "frontendQuestionId": "99", "paidOnly": false, "title": "Recover Binary Search Tree", "titleSlug": "recover-binary-search-tree", "topicTags": [{"name": "Tree", "id": "VG9waWNUYWdOb2RlOjIw", "slug": "tree"}, {"name": "Depth-First Search", "id": "VG9waWNUYWdOb2RlOjIx", "slug": "depth-first-search"}, {"name": "Binary Search Tree", "id": "VG9waWNUYWdOb2RlOjMw", "slug": "binary-search-tree"}, {"name": "Binary Tree", "id": "VG9waWNUYWdOb2RlOjYxMDU3", "slug": "binary-tree"}], "hasSolution": true, "hasVideoSolution": false, "totalAcceptedRaw": 625611, "totalSubmissionRaw": 1070689}, "100": {"acRate": 66.4047910507411, "difficulty": "Easy", "likes": 12709, "dislikes": 291, "categoryTitle": "Algorithms", "frontendQuestionId": "100", "paidOnly": false, "title": "Same Tree", "titleSlug": "same-tree", "topicTags": [{"name": "Tree", "id": "VG9waWNUYWdOb2RlOjIw", "slug": "tree"}, {"name": "Depth-First Search", "id": "VG9waWNUYWdOb2RlOjIx", "slug": "depth-first-search"}, {"name": "Breadth-First Search", "id": "VG9waWNUYWdOb2RlOjIy", "slug": "breadth-first-search"}, {"name": "Binary Tree", "id": "VG9waWNUYWdOb2RlOjYxMDU3", "slug": "binary-tree"}], "hasSolution": true, "hasVideoSolution": true, "totalAcceptedRaw": 3218431, "totalSubmissionRaw": 4846691}}